Workbook

Sheet 项目信息
A1: =T(B22)
A2: =T(B23)
A4: 工程信息
A5: 项目名称 | B5: DEMO-C项目C | E5: 项目编号
A6: 描述 | E6: 报价交期
A7: 报价单号 | B7: DEMO-QUOTE
A8: 报价人 | B8: 报价员A
A9: 创建日期 | B9: 2026.02.02
A10: 报价审核人
A11: 项目负责人
A12: 项目备注
A13: 客户信息
A14: 客户名称
A15: 联系人
A16: 联系电话
A17: 客户地址
A18: 客户邮编
A19: 客户网址
A20: 客户email
A21: 本企业信息
A22: 单位名称 | B22: 某成套设备有限公司
A23: 英文名称 | B23: Anonymized Switchgear Co.,Ltd
A24: 联系人 | B24: 宋楠
A25: 联系电话 | B25: 6.9198511e+09
A26: 销售地区 | B26: 全国
A27: 分类汇总 金额单位：人民币元
A28: 序号 | B28: 分类名称 | C28: 箱柜数量 | D28: 总 价 | E28: 成本 | F28: 毛利 | G28: 毛利率 | H28: 分类属性
A29: =ROW()-ROW(A$28) | B29: =MID(CELL("filename",folderTablee32ba25eda8d4a59a0a0201137327f11),SEARCH({"xlsx]",".xls]"},CELL("filename",folderTablee32ba25eda8d4a59a0a0201137327f11))+5,31) | C29: =IF(H29="箱变",低压柜!F107,低压柜!F103*IF(低压柜!F107="",1,低压柜!F107)) | D29: =ROUND(低压柜!H107,2) | E29: =ROUND(低压柜!J107,2) | F29: =ROUND((D29-E29),2) | G29: =IF(D29=0,0,F29/D29) | H29: =IF(OR(ISNUMBER(FIND("箱变",B29))=TRUE,ISNUMBER(FIND("欧变",B29))=TRUE,ISNUMBER(FIND("美变",B29))=TRUE,ISNUMBER(FIND("KVA",UPPER(B29)))=TRUE,ISNUMBER(FIND("箱式变电",B29))=TRUE),"箱变","常规")
A30: =ROW()-ROW(A$28)
A31: =ROW()-ROW(A$28)
A32: =ROW()-ROW(A$28)
A33: =ROW()-ROW(A$28)
A34: =ROW()-ROW(A$28)
A35: =ROW()-ROW(A$28)
A36: =ROW()-ROW(A$28)
A37: =ROW()-ROW(A$28)
A38: =ROW()-ROW(A$28)
A39: =ROW()-ROW(A$28)
A40: =ROW()-ROW(A$28)
A41: =ROW()-ROW(A$28)
... A52: =ROW()-ROW(A$28)
A53: =ROW()-ROW(A$28) | B53: 小计 | C53: =ROUND(SUM(C28:INDEX(C:C,ROW()-1)),2) | D53: =ROUND(SUM(D28:INDEX(D:D,ROW()-1)),2) | E53: =ROUND(SUM(E28:INDEX(E:E,ROW()-1)),2) | F53: =SUM(F28:INDEX(F:F,ROW()-1)) | G53: =IF(D53=0,0,F53/D53) | H53: =SUM(H28:INDEX(H:H,ROW()-1))
A54: =ROW()-ROW(A$28) | B54: 运费 | D54: 0
A55: =ROW()-ROW(A$28) | B55: 合计 | D55: =ROUND(SUM(D53:D54),2)
A56: =ROW()-ROW(A$28) | B56: 人民币大写 | C56: =TEXT(SUBSTITUTE(IF(D55="","",IF(MOD(D55,1)=0,TEXT(INT(D55),"[DBNum2][$-804]G/通用格式元整"),(TEXT(INT(D55),"[DBNum2][$-804]G/通用格式元")&TEXT((INT(D55*10)-INT(D55)*10),"[DBNum2][$-804]G/通用格式角")&TEXT((INT(D55*100)-INT(D55*10)*10),"[DBNum2][$-804]G/通用格式分")))),"零角","零"),)
A57: 报表说明 | B57: 1.柜型配置：柜体采用BlokSeT，188+16台，分隔类型Form 3b，防护等级IP3X； 2.进出线&维护方式：主配电铜排侧进，电罩箱段电缆上进，母线、电缆上出；后维护 3.柜体尺寸：高度2200mm，深度1200mm，宽度BlokSeT标准； 4.铜排处理：所有母线均为裸铜排，无外包绝缘。 5.铜排规格配置：母线规格及技术参数如下： 5.1 2500KVA变压器低压配电系统，水平母线额定电流为5000A，额定短时耐受电流为100KA，母线规格为TMY-4*(4*150*5)+2*(50*5)。 5.2 4*600KVA UPS低压系统：母线额定电流为4000A，额定短时耐受电流为65kA，母线规格为TMY-4*5*125*5+2*(50*5)。 5.3 3*600KVA UPS低压系统：母线额定电流为3200A，额定短时耐受电流为65kA，母线规格为TMY-4*3*(125*5)+2*(50*5)。 5.4 3*500KVA UPS低压系统：母线额定电流为2500A，额定短时耐受电流为50kA，母线规格为TMY-4*2*125*5+1*(50*5)。 5.5 2*600，2*500KVA UPS低压系统：母线额定电流为2000A，额定短时耐受电流为50kA，母线规格为TMY-4*2*(100*5)+1*(50*5)。 5.6 2*400KVA UPS低压系统：母线额定电流为1600A，额定短时耐受电流为50kA，母线规格为TMY-4*2*80*5+1*(50*5)。 5.7 600KVA UPS低压系统：母线额定电流为1250A，额定短时耐受电流为50kA，母线规格为TMY-4*100*5+1*(50*5)。 5.8 400/500KVA UPS低压系统：母线额定电流为1000A，额定短时耐受电流为50kA，母线规格为TMY-4*100*5+1*(50*5)。 6.框架断路器配置：型号MT，分断能力100/66/65kA（N1a型短时耐受能力为50kA/s），极数按招标图纸，控制单元变压器低压进线Mic6.0D LSIG、其它为Mic5.0E LSI，操作方式手动&电动，无本体通讯，电气量&开关量通过表计上传，安装方式抽出式； 7.塑壳断路器配置：型号NSX，分断能力70kA，极数按招标图纸，保护单元250A及以下采用TMD热磁式；400A及以上采用Mic2.3电子式，操作方式手动，无本体通讯，电气量&开关量通过表计上传，塑壳安装方式插拔式。 8.仪表配置：变压器低压进线采用施耐德PM5350P产品，其它采用施耐德PM4101产品； 9.无功补偿配置：补偿方式为SVG静止无功发生器，SVG采用甲供产品，乙方负责安装接线，主开关采用刀熔开关，极数3P。 10.浪涌保护配置：浪涌采用施耐德iPRD、iPRF或iPRU系列，配ISCB1或ISCB2专用后备保护； 11.有源滤波配置：有源滤波采用甲供，主开关采用刀熔开关； 12.进线、母联切换方式：采用PLC自动投切方式。 13.双电源ATS配置：ATS开关采用施耐德WTS系列，极数4P，PC级，配套D型控制器。 14.变频回路配置：变频器采用施耐德ATV630系列产品，主开关采用施耐德NSX系列塑壳断路器，出线配置DV/DT滤波器； 15.软起回路配置：软起采用施耐德ATS480系列产品，主开关采用施耐德NSX系列隔离开关； 16.母线桥接口：开关柜与母线的连接方案为开关柜母线伸出柜外200mm并预留开孔。 17.涉及到1、叠装方案只适用于MT06-12；2、单ACB适用于06-16，这两种情况的方案，柜宽需要改为400mm

Sheet 低压柜
A2: =T(项目信息!B22)
A3: =T(项目信息!B23)
A4: 成套产品报价清单 金额单位：人民币元
A5: =CONCATENATE("项目名称:",项目信息!B5) | H5: =CONCATENATE("报价序号:",项目信息!B7)
A6: 序号 | B6: 柜号 | C6: 箱柜名称 | D6: 箱柜型号 | E6: 单位 | F6: 数量 | G6: 单 价 | H6: 总 价 | I6: 备注 | J6: 成本总价 | K6: 毛利 | L6: 毛利率 | M6: 箱柜尺寸 | N6: 类别 | O6: 预留 | P6: 预留 | Q6: 图号
A7: =ROW()-ROW(A$6) | B7: AAN1-01、BAN2-01 | C7: 进线柜 | D7: BlokSeT | E7: 台 | F7: 2 | G7: =ROUND(H143,2) | H7: =ROUND(F7*G7,2) | J7: =ROUND(K144,2) | K7: =ROUND(H7-J7,2) | L7: =IF(H7=0,0,K7/H7) | M7: 1200W*1200D*2200H | N7: 低压固定柜
A8: =ROW()-ROW(A$6) | B8: AAN1-02、BAN2-02 | C8: 联络柜 | D8: BlokSeT | E8: 台 | F8: 2 | G8: =ROUND(H172,2) | H8: =ROUND(F8*G8,2) | J8: =ROUND(K173,2) | K8: =ROUND(H8-J8,2) | L8: =IF(H8=0,0,K8/H8) | M8: 700W*1200D*2200H | N8: 低压固定柜
A9: =ROW()-ROW(A$6) | B9: AAN1-03-1、BAN2-03-1 | C9: 电容柜 | D9: BlokSeT | E9: 台 | F9: 2 | G9: =ROUND(H200,2) | H9: =ROUND(F9*G9,2) | J9: =ROUND(K201,2) | K9: =ROUND(H9-J9,2) | L9: =IF(H9=0,0,K9/H9) | M9: 800W*1200D*2200H | N9: 低压固定柜
A10: =ROW()-ROW(A$6) | B10: AAN1-03-2、BAN2-03-2 | C10: 电容柜 | D10: BlokSeT | E10: 台 | F10: 2 | G10: =ROUND(H228,2) | H10: =ROUND(F10*G10,2) | J10: =ROUND(K229,2) | K10: =ROUND(H10-J10,2) | L10: =IF(H10=0,0,K10/H10) | M10: 800W*1200D*2200H | N10: 低压固定柜
A11: =ROW()-ROW(A$6) | B11: AAN1-04、BAN2-04 | C11: 有源滤波柜 | D11: BlokSeT | E11: 台 | F11: 2 | G11: =ROUND(H255,2) | H11: =ROUND(F11*G11,2) | J11: =ROUND(K256,2) | K11: =ROUND(H11-J11,2) | L11: =IF(H11=0,0,K11/H11) | M11: 800W*1200D*2200H | N11: 低压固定柜
A12: =ROW()-ROW(A$6) | B12: AAN1-05、BAN2-05 | C12: 馈线柜 | D12: BlokSeT | E12: 台 | F12: 2 | G12: =ROUND(H286,2) | H12: =ROUND(F12*G12,2) | J12: =ROUND(K287,2) | K12: =ROUND(H12-J12,2) | L12: =IF(H12=0,0,K12/H12) | M12: 800W*1200D*2200H | N12: 低压固定柜
A13: =ROW()-ROW(A$6) | B13: AAN1-06、BAN2-06 | C13: 馈线柜 | D13: BlokSeT | E13: 台 | F13: 2 | G13: =ROUND(H317,2) | H13: =ROUND(F13*G13,2) | J13: =ROUND(K318,2) | K13: =ROUND(H13-J13,2) | L13: =IF(H13=0,0,K13/H13) | M13: 800W*1200D*2200H | N13: 低压固定柜
A14: =ROW()-ROW(A$6) | B14: AAN1-07 | C14: 馈线柜 | D14: BlokSeT | E14: 台 | F14: 1 | G14: =ROUND(H350,2) | H14: =ROUND(F14*G14,2) | J14: =ROUND(K351,2) | K14: =ROUND(H14-J14,2) | L14: =IF(H14=0,0,K14/H14) | M14: 800W*1200D*2200H | N14: 低压固定柜
A15: =ROW()-ROW(A$6) | B15: AAN1-08 | C15: 馈线柜 | D15: BlokSeT | E15: 台 | F15: 1 | G15: =ROUND(H382,2) | H15: =ROUND(F15*G15,2) | J15: =ROUND(K383,2) | K15: =ROUND(H15-J15,2) | L15: =IF(H15=0,0,K15/H15) | M15: 600W*1200D*2200H | N15: 低压固定柜
A16: =ROW()-ROW(A$6) | B16: AAN1-09 | C16: 馈线柜 | D16: BlokSeT | E16: 台 | F16: 1 | G16: =ROUND(H413,2) | H16: =ROUND(F16*G16,2) | J16: =ROUND(K414,2) | K16: =ROUND(H16-J16,2) | L16: =IF(H16=0,0,K16/H16) | M16: 600W*1200D*2200H | N16: 低压固定柜
A17: =ROW()-ROW(A$6) | B17: BAN1-07 | C17: 馈线柜 | D17: BlokSeT | E17: 台 | F17: 1 | G17: =ROUND(H446,2) | H17: =ROUND(F17*G17,2) | J17: =ROUND(K447,2) | K17: =ROUND(H17-J17,2) | L17: =IF(H17=0,0,K17/H17) | M17: 800W*1200D*2200H | N17: 低压固定柜
A18: =ROW()-ROW(A$6) | B18: BAN1-08 | C18: 馈线柜 | D18: BlokSeT | E18: 台 | F18: 1 | G18: =ROUND(H476,2) | H18: =ROUND(F18*G18,2) | J18: =ROUND(K477,2) | K18: =ROUND(H18-J18,2) | L18: =IF(H18=0,0,K18/H18) | M18: 600W*1200D*2200H | N18: 低压固定柜
A19: =ROW()-ROW(A$6) | B19: BAN1-09 | C19: 馈线柜 | D19: BlokSeT | E19: 台 | F19: 1 | G19: =ROUND(H511,2) | H19: =ROUND(F19*G19,2) | J19: =ROUND(K512,2) | K19: =ROUND(H19-J19,2) | L19: =IF(H19=0,0,K19/H19) | M19: 600W*1200D*2200H | N19: 低压固定柜
A20: =ROW()-ROW(A$6) | B20: AAN3-01、BAN4-01 | C20: 进线柜 | D20: BlokSeT | E20: 台 | F20: 2 | G20: =ROUND(H546,2) | H20: =ROUND(F20*G20,2) | J20: =ROUND(K547,2) | K20: =ROUND(H20-J20,2) | L20: =IF(H20=0,0,K20/H20) | M20: 700W*1200D*2200H | N20: 低压固定柜
A21: =ROW()-ROW(A$6) | B21: AAN3-02、BAN4-02 | C21: 电容柜 | D21: BlokSeT | E21: 台 | F21: 2 | G21: =ROUND(H574,2) | H21: =ROUND(F21*G21,2) | J21: =ROUND(K575,2) | K21: =ROUND(H21-J21,2) | L21: =IF(H21=0,0,K21/H21) | M21: 800W*1200D*2200H | N21: 低压固定柜
A22: =ROW()-ROW(A$6) | B22: AAN3-03、BAN4-03 | C22: 馈线柜 | D22: BlokSeT | E22: 台 | F22: 2 | G22: =ROUND(H605,2) | H22: =ROUND(F22*G22,2) | J22: =ROUND(K606,2) | K22: =ROUND(H22-J22,2) | L22: =IF(H22=0,0,K22/H22) | M22: 400W*1200D*2200H | N22: 低压固定柜
A23: =ROW()-ROW(A$6) | B23: AAN3-04 | C23: 馈线柜 | D23: BlokSeT | E23: 台 | F23: 1 | G23: =ROUND(H639,2) | H23: =ROUND(F23*G23,2) | J23: =ROUND(K640,2) | K23: =ROUND(H23-J23,2) | L23: =IF(H23=0,0,K23/H23) | M23: 400W*1200D*2200H | N23: 低压固定柜
A24: =ROW()-ROW(A$6) | B24: AAN3-05 | C24: 馈线柜 | D24: BlokSeT | E24: 台 | F24: 1 | G24: =ROUND(H673,2) | H24: =ROUND(F24*G24,2) | J24: =ROUND(K674,2) | K24: =ROUND(H24-J24,2) | L24: =IF(H24=0,0,K24/H24) | M24: 800W*1200D*2200H | N24: 低压固定柜
A25: =ROW()-ROW(A$6) | B25: AAN3-06、BAN4-06 | C25: 馈线柜 | D25: BlokSeT | E25: 台 | F25: 2 | G25: =ROUND(H701,2) | H25: =ROUND(F25*G25,2) | J25: =ROUND(K702,2) | K25: =ROUND(H25-J25,2) | L25: =IF(H25=0,0,K25/H25) | M25: 700W*1200D*2200H | N25: 低压固定柜
A26: =ROW()-ROW(A$6) | B26: AAN3-07、BAN4-07 | C26: 联络柜 | D26: BlokSeT | E26: 台 | F26: 2 | G26: =ROUND(H730,2) | H26: =ROUND(F26*G26,2) | J26: =ROUND(K731,2) | K26: =ROUND(H26-J26,2) | L26: =IF(H26=0,0,K26/H26) | M26: 700W*1200D*2200H | N26: 低压固定柜
A27: =ROW()-ROW(A$6) | B27: BAN4-05 | C27: 馈线柜 | D27: BlokSeT | E27: 台 | F27: 1 | G27: =ROUND(H764,2) | H27: =ROUND(F27*G27,2) | J27: =ROUND(K765,2) | K27: =ROUND(H27-J27,2) | L27: =IF(H27=0,0,K27/H27) | M27: 600W*1200D*2200H | N27: 低压固定柜
A28: =ROW()-ROW(A$6) | B28: BAN4-04 | C28: 馈线柜 | D28: BlokSeT | E28: 台 | F28: 1 | G28: =ROUND(H800,2) | H28: =ROUND(F28*G28,2) | J28: =ROUND(K801,2) | K28: =ROUND(H28-J28,2) | L28: =IF(H28=0,0,K28/H28) | M28: 600W*1200D*2200H | N28: 低压固定柜
A29: =ROW()-ROW(A$6) | B29: AAN5-01、BAN6-01、AAN7-01、BAN8-01 | C29: 进线柜 | D29: BlokSeT | E29: 台 | F29: 4 | G29: =ROUND(H835,2) | H29: =ROUND(F29*G29,2) | J29: =ROUND(K836,2) | K29: =ROUND(H29-J29,2) | L29: =IF(H29=0,0,K29/H29) | M29: 1200W*1200D*2200H | N29: 低压固定柜
A30: =ROW()-ROW(A$6) | B30: AAN5-02、BAN6-02、AAN7-03、BAN8-03 | C30: 电容柜 | D30: BlokSeT | E30: 台 | F30: 4 | G30: =ROUND(H863,2) | H30: =ROUND(F30*G30,2) | J30: =ROUND(K864,2) | K30: =ROUND(H30-J30,2) | L30: =IF(H30=0,0,K30/H30) | M30: 800W*1200D*2200H | N30: 低压固定柜
A31: =ROW()-ROW(A$6) | B31: AAN5-03 | C31: 馈线柜 | D31: BlokSeT | E31: 台 | F31: 1 | G31: =ROUND(H895,2) | H31: =ROUND(F31*G31,2) | J31: =ROUND(K896,2) | K31: =ROUND(H31-J31,2) | L31: =IF(H31=0,0,K31/H31) | M31: 600W*1200D*2200H | N31: 低压固定柜
A32: =ROW()-ROW(A$6) | B32: AAN5-04、BAN6-04、AAN7-04~06、BAN8-05~07 | C32: 馈线柜 | D32: BlokSeT | E32: 台 | F32: 8 | G32: =ROUND(H926,2) | H32: =ROUND(F32*G32,2) | J32: =ROUND(K927,2) | K32: =ROUND(H32-J32,2) | L32: =IF(H32=0,0,K32/H32) | M32: 400W*1200D*2200H | N32: 低压固定柜
A33: =ROW()-ROW(A$6) | B33: AAN5-05 | C33: 馈线柜 | D33: BlokSeT | E33: 台 | F33: 1 | G33: =ROUND(H960,2) | H33: =ROUND(F33*G33,2) | J33: =ROUND(K961,2) | K33: =ROUND(H33-J33,2) | L33: =IF(H33=0,0,K33/H33) | M33: 400W*1200D*2200H | N33: 低压固定柜
A34: =ROW()-ROW(A$6) | B34: AAN5-06、BAN6-06、AAN7-07、BAN8-08 | C34: 馈线柜 | D34: BlokSeT | E34: 台 | F34: 4 | G34: =ROUND(H989,2) | H34: =ROUND(F34*G34,2) | J34: =ROUND(K990,2) | K34: =ROUND(H34-J34,2) | L34: =IF(H34=0,0,K34/H34) | M34: 700W*1200D*2200H | N34: 低压固定柜
A35: =ROW()-ROW(A$6) | B35: AAN5-07、BAN6-07、AAN7-08、BAN8-04 | C35: 馈线柜 | D35: BlokSeT | E35: 台 | F35: 4 | G35: =ROUND(H1017,2) | H35: =ROUND(F35*G35,2) | J35: =ROUND(K1018,2) | K35: =ROUND(H35-J35,2) | L35: =IF(H35=0,0,K35/H35) | M35: 700W*1200D*2200H | N35: 低压固定柜
A36: =ROW()-ROW(A$6) | B36: AAN5-08、BAN6-08、AAN7-02、BAN8-02 | C36: 联络柜 | D36: BlokSeT | E36: 台 | F36: 4 | G36: =ROUND(H1046,2) | H36: =ROUND(F36*G36,2) | J36: =ROUND(K1047,2) | K36: =ROUND(H36-J36,2) | L36: =IF(H36=0,0,K36/H36) | M36: 700W*1200D*2200H | N36: 低压固定柜
A37: =ROW()-ROW(A$6) | B37: BAN6-05 | C37: 馈线柜 | D37: BlokSeT | E37: 台 | F37: 1 | G37: =ROUND(H1080,2) | H37: =ROUND(F37*G37,2) | J37: =ROUND(K1081,2) | K37: =ROUND(H37-J37,2) | L37: =IF(H37=0,0,K37/H37) | M37: 600W*1200D*2200H | N37: 低压固定柜
A38: =ROW()-ROW(A$6) | B38: BAN6-03 | C38: 馈线柜 | D38: BlokSeT | E38: 台 | F38: 1 | G38: =ROUND(H1111,2) | H38: =ROUND(F38*G38,2) | J38: =ROUND(K1112,2) | K38: =ROUND(H38-J38,2) | L38: =IF(H38=0,0,K38/H38) | M38: 600W*1200D*2200H | N38: 低压固定柜
A39: =ROW()-ROW(A$6) | B39: AAN9-01、BAN10-01、AAN11-01、BAN12-01 | C39: 进线柜 | D39: BlokSeT | E39: 台 | F39: 4 | G39: =ROUND(H1146,2) | H39: =ROUND(F39*G39,2) | J39: =ROUND(K1147,2) | K39: =ROUND(H39-J39,2) | L39: =IF(H39=0,0,K39/H39) | M39: 1200W*1200D*2200H | N39: 低压固定柜
A40: =ROW()-ROW(A$6) | B40: AAN9-02、BAN10-02、AAN11-02、BAN12-02 | C40: 联络柜 | D40: BlokSeT | E40: 台 | F40: 4 | G40: =ROUND(H1175,2) | H40: =ROUND(F40*G40,2) | J40: =ROUND(K1176,2) | K40: =ROUND(H40-J40,2) | L40: =IF(H40=0,0,K40/H40) | M40: 700W*1200D*2200H | N40: 低压固定柜
A41: =ROW()-ROW(A$6) | B41: AAN9-03、BAN10-03、AAN11-03、BAN12-03 | C41: 电容柜 | D41: BlokSeT | E41: 台 | F41: 4 | G41: =ROUND(H1203,2) | H41: =ROUND(F41*G41,2) | J41: =ROUND(K1204,2) | K41: =ROUND(H41-J41,2) | L41: =IF(H41=0,0,K41/H41) | M41: 800W*1200D*2200H | N41: 低压固定柜
A42: =ROW()-ROW(A$6) | B42: AAN9-04 | C42: 馈线柜 | D42: BlokSeT | E42: 台 | F42: 1 | G42: =ROUND(H1235,2) | H42: =ROUND(F42*G42,2) | J42: =ROUND(K1236,2) | K42: =ROUND(H42-J42,2) | L42: =IF(H42=0,0,K42/H42) | M42: 600W*1200D*2200H | N42: 低压固定柜
A43: =ROW()-ROW(A$6) | B43: AAN9-05、BAN10-05、AAN11-05、BAN12-05 | C43: 馈线柜 | D43: BlokSeT | E43: 台 | F43: 4 | G43: =ROUND(H1266,2) | H43: =ROUND(F43*G43,2) | J43: =ROUND(K1267,2) | K43: =ROUND(H43-J43,2) | L43: =IF(H43=0,0,K43/H43) | M43: 400W*1200D*2200H | N43: 低压固定柜
A44: =ROW()-ROW(A$6) | B44: AAN9-06、BAN10-06、AAN11-06、BAN12-06 | C44: 馈线柜 | D44: BlokSeT | E44: 台 | F44: 4 | G44: =ROUND(H1300,2) | H44: =ROUND(F44*G44,2) | J44: =ROUND(K1301,2) | K44: =ROUND(H44-J44,2) | L44: =IF(H44=0,0,K44/H44) | M44: 600W*1200D*2200H | N44: 低压固定柜
A45: =ROW()-ROW(A$6) | B45: AAN9-07、BAN10-07、AAN11-07、BAN12-07 | C45: 馈线柜 | D45: BlokSeT | E45: 台 | F45: 4 | G45: =ROUND(H1329,2) | H45: =ROUND(F45*G45,2) | J45: =ROUND(K1330,2) | K45: =ROUND(H45-J45,2) | L45: =IF(H45=0,0,K45/H45) | M45: 700W*1200D*2200H | N45: 低压固定柜
A46: =ROW()-ROW(A$6) | B46: AAN9-08、BAN10-08、AAN11-08、BAN12-08 | C46: 馈线柜 | D46: BlokSeT | E46: 台 | F46: 4 | G46: =ROUND(H1357,2) | H46: =ROUND(F46*G46,2) | J46: =ROUND(K1358,2) | K46: =ROUND(H46-J46,2) | L46: =IF(H46=0,0,K46/H46) | M46: 700W*1200D*2200H | N46: 低压固定柜
A47: =ROW()-ROW(A$6) | B47: BAN10-04 | C47: 馈线柜 | D47: BlokSeT | E47: 台 | F47: 1 | G47: =ROUND(H1390,2) | H47: =ROUND(F47*G47,2) | J47: =ROUND(K1391,2) | K47: =ROUND(H47-J47,2) | L47: =IF(H47=0,0,K47/H47) | M47: 800W*1200D*2200H | N47: 低压固定柜
A48: =ROW()-ROW(A$6) | B48: AAN11-04 | C48: 馈线柜 | D48: BlokSeT | E48: 台 | F48: 1 | G48: =ROUND(H1423,2) | H48: =ROUND(F48*G48,2) | J48: =ROUND(K1424,2) | K48: =ROUND(H48-J48,2) | L48: =IF(H48=0,0,K48/H48) | M48: 600W*1200D*2200H | N48: 低压固定柜
A49: =ROW()-ROW(A$6) | B49: BAN12-04 | C49: 馈线柜 | D49: BlokSeT | E49: 台 | F49: 1 | G49: =ROUND(H1455,2) | H49: =ROUND(F49*G49,2) | J49: =ROUND(K1456,2) | K49: =ROUND(H49-J49,2) | L49: =IF(H49=0,0,K49/H49) | M49: 600W*1200D*2200H | N49: 低压固定柜
A50: =ROW()-ROW(A$6) | B50: AAN13-01、BAN14-01 | C50: 进线柜 | D50: BlokSeT | E50: 台 | F50: 2 | G50: =ROUND(H1488,2) | H50: =ROUND(F50*G50,2) | J50: =ROUND(K1489,2) | K50: =ROUND(H50-J50,2) | L50: =IF(H50=0,0,K50/H50) | M50: 700W*1200D*2200H | N50: 低压固定柜
A51: =ROW()-ROW(A$6) | B51: AAN13-02、BAN14-02 | C51: 电容柜 | D51: BlokSeT | E51: 台 | F51: 2 | G51: =ROUND(H1516,2) | H51: =ROUND(F51*G51,2) | J51: =ROUND(K1517,2) | K51: =ROUND(H51-J51,2) | L51: =IF(H51=0,0,K51/H51) | M51: 800W*1200D*2200H | N51: 低压固定柜
A52: =ROW()-ROW(A$6) | B52: AAN13-03、BAN14-03 | C52: 联络柜 | D52: BlokSeT | E52: 台 | F52: 2 | G52: =ROUND(H1544,2) | H52: =ROUND(F52*G52,2) | J52: =ROUND(K1545,2) | K52: =ROUND(H52-J52,2) | L52: =IF(H52=0,0,K52/H52) | M52: 700W*1200D*2200H | N52: 低压固定柜
A53: =ROW()-ROW(A$6) | B53: AAN13-04、BAN14-04 | C53: 馈线柜 | D53: BlokSeT | E53: 台 | F53: 2 | G53: =ROUND(H1572,2) | H53: =ROUND(F53*G53,2) | J53: =ROUND(K1573,2) | K53: =ROUND(H53-J53,2) | L53: =IF(H53=0,0,K53/H53) | M53: 700W*1200D*2200H | N53: 低压固定柜
A54: =ROW()-ROW(A$6) | B54: AAN13-05、BAN14-05 | C54: 馈线柜 | D54: BlokSeT | E54: 台 | F54: 2 | G54: =ROUND(H1603,2) | H54: =ROUND(F54*G54,2) | J54: =ROUND(K1604,2) | K54: =ROUND(H54-J54,2) | L54: =IF(H54=0,0,K54/H54) | M54: 400W*1200D*2200H | N54: 低压固定柜
A55: =ROW()-ROW(A$6) | B55: AAN13-06 | C55: 馈线柜 | D55: BlokSeT | E55: 台 | F55: 1 | G55: =ROUND(H1637,2) | H55: =ROUND(F55*G55,2) | J55: =ROUND(K1638,2) | K55: =ROUND(H55-J55,2) | L55: =IF(H55=0,0,K55/H55) | M55: 600W*1200D*2200H | N55: 低压固定柜
A56: =ROW()-ROW(A$6) | B56: BAN14-06 | C56: 馈线柜 | D56: BlokSeT | E56: 台 | F56: 1 | G56: =ROUND(H1671,2) | H56: =ROUND(F56*G56,2) | J56: =ROUND(K1672,2) | K56: =ROUND(H56-J56,2) | L56: =IF(H56=0,0,K56/H56) | M56: 600W*1200D*2200H | N56: 低压固定柜
A57: =ROW()-ROW(A$6) | B57: T3-AU11、T4-BU11 | C57: 进线柜 | D57: BlokSeT | E57: 台 | F57: 2 | G57: =ROUND(H1702,2) | H57: =ROUND(F57*G57,2) | J57: =ROUND(K1703,2) | K57: =ROUND(H57-J57,2) | L57: =IF(H57=0,0,K57/H57) | M57: 400W*1200D*2200H | N57: 低压固定柜
A58: =ROW()-ROW(A$6) | B58: T3-AU12、T4-BU12 | C58: 进线柜 | D58: BlokSeT | E58: 台 | F58: 2 | G58: =ROUND(H1736,2) | H58: =ROUND(F58*G58,2) | J58: =ROUND(K1737,2) | K58: =ROUND(H58-J58,2) | L58: =IF(H58=0,0,K58/H58) | M58: 400W*1200D*2200H | N58: 低压固定柜
A59: =ROW()-ROW(A$6) | B59: T3-AU13、T4-BU13 | C59: 馈线柜 | D59: BlokSeT | E59: 台 | F59: 2 | G59: =ROUND(H1764,2) | H59: =ROUND(F59*G59,2) | J59: =ROUND(K1765,2) | K59: =ROUND(H59-J59,2) | L59: =IF(H59=0,0,K59/H59) | M59: 600W*1200D*2200H | N59: 低压固定柜
A60: =ROW()-ROW(A$6) | B60: T3-AU14、T4-BU14 | C60: 馈线柜 | D60: BlokSeT | E60: 台 | F60: 2 | G60: =ROUND(H1792,2) | H60: =ROUND(F60*G60,2) | J60: =ROUND(K1793,2) | K60: =ROUND(H60-J60,2) | L60: =IF(H60=0,0,K60/H60) | M60: 600W*1200D*2200H | N60: 低压固定柜
A61: =ROW()-ROW(A$6) | B61: T5-AU11、T6-BU11 | C61: 进线柜 | D61: BlokSeT | E61: 台 | F61: 2 | G61: =ROUND(H1823,2) | H61: =ROUND(F61*G61,2) | J61: =ROUND(K1824,2) | K61: =ROUND(H61-J61,2) | L61: =IF(H61=0,0,K61/H61) | M61: 400W*1200D*2200H | N61: 低压固定柜
A62: =ROW()-ROW(A$6) | B62: T5-AU12、T6-BU12 | C62: 进线柜 | D62: BlokSeT | E62: 台 | F62: 2 | G62: =ROUND(H1857,2) | H62: =ROUND(F62*G62,2) | J62: =ROUND(K1858,2) | K62: =ROUND(H62-J62,2) | L62: =IF(H62=0,0,K62/H62) | M62: 400W*1200D*2200H | N62: 低压固定柜
A63: =ROW()-ROW(A$6) | B63: T5-AU13、T5-AU14、T6-BU13、T6-BU14 | C63: 馈线柜 | D63: BlokSeT | E63: 台 | F63: 4 | G63: =ROUND(H1885,2) | H63: =ROUND(F63*G63,2) | J63: =ROUND(K1886,2) | K63: =ROUND(H63-J63,2) | L63: =IF(H63=0,0,K63/H63) | M63: 600W*1200D*2200H | N63: 低压固定柜
A64: =ROW()-ROW(A$6) | B64: T5-AU21、T6-BU21 | C64: 进线柜 | D64: BlokSeT | E64: 台 | F64: 2 | G64: =ROUND(H1919,2) | H64: =ROUND(F64*G64,2) | J64: =ROUND(K1920,2) | K64: =ROUND(H64-J64,2) | L64: =IF(H64=0,0,K64/H64) | M64: 400W*1200D*2200H | N64: 低压固定柜
A65: =ROW()-ROW(A$6) | B65: T5-AU22、T6-BU22 | C65: 馈线柜 | D65: BlokSeT | E65: 台 | F65: 2 | G65: =ROUND(H1947,2) | H65: =ROUND(F65*G65,2) | J65: =ROUND(K1948,2) | K65: =ROUND(H65-J65,2) | L65: =IF(H65=0,0,K65/H65) | M65: 600W*1200D*2200H | N65: 低压固定柜
A66: =ROW()-ROW(A$6) | B66: T7-AU11、T8-BU11 | C66: 进线柜 | D66: BlokSeT | E66: 台 | F66: 2 | G66: =ROUND(H1978,2) | H66: =ROUND(F66*G66,2) | J66: =ROUND(K1979,2) | K66: =ROUND(H66-J66,2) | L66: =IF(H66=0,0,K66/H66) | M66: 400W*1200D*2200H | N66: 低压固定柜
A67: =ROW()-ROW(A$6) | B67: T7-AU12、T5-BU12 | C67: 进线柜 | D67: BlokSeT | E67: 台 | F67: 2 | G67: =ROUND(H2012,2) | H67: =ROUND(F67*G67,2) | J67: =ROUND(K2013,2) | K67: =ROUND(H67-J67,2) | L67: =IF(H67=0,0,K67/H67) | M67: 400W*1200D*2200H | N67: 低压固定柜
A68: =ROW()-ROW(A$6) | B68: T7-AU13、T7-AU14、T8-BU13、T8-BU14 | C68: 馈线柜 | D68: BlokSeT | E68: 台 | F68: 4 | G68: =ROUND(H2040,2) | H68: =ROUND(F68*G68,2) | J68: =ROUND(K2041,2) | K68: =ROUND(H68-J68,2) | L68: =IF(H68=0,0,K68/H68) | M68: 600W*1200D*2200H | N68: 低压固定柜
A69: =ROW()-ROW(A$6) | B69: T7-AU21、T8-BU21 | C69: 进线柜 | D69: BlokSeT | E69: 台 | F69: 2 | G69: =ROUND(H2075,2) | H69: =ROUND(F69*G69,2) | J69: =ROUND(K2076,2) | K69: =ROUND(H69-J69,2) | L69: =IF(H69=0,0,K69/H69) | M69: 400W*1200D*2200H | N69: 低压固定柜
A70: =ROW()-ROW(A$6) | B70: T7-AU22、T7-AU23、T8-BU22、T8-BU23 | C70: 馈线柜 | D70: BlokSeT | E70: 台 | F70: 4 | G70: =ROUND(H2103,2) | H70: =ROUND(F70*G70,2) | J70: =ROUND(K2104,2) | K70: =ROUND(H70-J70,2) | L70: =IF(H70=0,0,K70/H70) | M70: 600W*1200D*2200H | N70: 低压固定柜
A71: =ROW()-ROW(A$6) | B71: T9-AU11、T10-BU11 | C71: 进线柜 | D71: BlokSeT | E71: 台 | F71: 2 | G71: =ROUND(H2134,2) | H71: =ROUND(F71*G71,2) | J71: =ROUND(K2135,2) | K71: =ROUND(H71-J71,2) | L71: =IF(H71=0,0,K71/H71) | M71: 400W*1200D*2200H | N71: 低压固定柜
A72: =ROW()-ROW(A$6) | B72: T9-AU12、T10-BU12 | C72: 进线柜 | D72: BlokSeT | E72: 台 | F72: 2 | G72: =ROUND(H2168,2) | H72: =ROUND(F72*G72,2) | J72: =ROUND(K2169,2) | K72: =ROUND(H72-J72,2) | L72: =IF(H72=0,0,K72/H72) | M72: 400W*1200D*2200H | N72: 低压固定柜
A73: =ROW()-ROW(A$6) | B73: T9-AU13、T9-AU14、T10-BU13、T10-BU14 | C73: 馈线柜 | D73: BlokSeT | E73: 台 | F73: 4 | G73: =ROUND(H2196,2) | H73: =ROUND(F73*G73,2) | J73: =ROUND(K2197,2) | K73: =ROUND(H73-J73,2) | L73: =IF(H73=0,0,K73/H73) | M73: 600W*1200D*2200H | N73: 低压固定柜
A74: =ROW()-ROW(A$6) | B74: T9-AU21、T10-BU21 | C74: 进线柜 | D74: BlokSeT | E74: 台 | F74: 2 | G74: =ROUND(H2231,2) | H74: =ROUND(F74*G74,2) | J74: =ROUND(K2232,2) | K74: =ROUND(H74-J74,2) | L74: =IF(H74=0,0,K74/H74) | M74: 400W*1200D*2200H | N74: 低压固定柜
A75: =ROW()-ROW(A$6) | B75: T9-AU22、T10-BU22 | C75: 馈线柜 | D75: BlokSeT | E75: 台 | F75: 2 | G75: =ROUND(H2259,2) | H75: =ROUND(F75*G75,2) | J75: =ROUND(K2260,2) | K75: =ROUND(H75-J75,2) | L75: =IF(H75=0,0,K75/H75) | M75: 600W*1200D*2200H | N75: 低压固定柜
A76: =ROW()-ROW(A$6) | B76: T11-AU11、T12-BU11 | C76: 进线柜 | D76: BlokSeT | E76: 台 | F76: 2 | G76: =ROUND(H2290,2) | H76: =ROUND(F76*G76,2) | J76: =ROUND(K2291,2) | K76: =ROUND(H76-J76,2) | L76: =IF(H76=0,0,K76/H76) | M76: 400W*1200D*2200H | N76: 低压固定柜
A77: =ROW()-ROW(A$6) | B77: T11-AU12、T12-BU12 | C77: 进线柜 | D77: BlokSeT | E77: 台 | F77: 2 | G77: =ROUND(H2324,2) | H77: =ROUND(F77*G77,2) | J77: =ROUND(K2325,2) | K77: =ROUND(H77-J77,2) | L77: =IF(H77=0,0,K77/H77) | M77: 400W*1200D*2200H | N77: 低压固定柜
A78: =ROW()-ROW(A$6) | B78: T11-AU13、T11-AU14、T12-BU13、T12-BU14 | C78: 馈线柜 | D78: BlokSeT | E78: 台 | F78: 4 | G78: =ROUND(H2352,2) | H78: =ROUND(F78*G78,2) | J78: =ROUND(K2353,2) | K78: =ROUND(H78-J78,2) | L78: =IF(H78=0,0,K78/H78) | M78: 600W*1200D*2200H | N78: 低压固定柜
A79: =ROW()-ROW(A$6) | B79: T11-AU21、T12-BU21 | C79: 进线柜 | D79: BlokSeT | E79: 台 | F79: 2 | G79: =ROUND(H2387,2) | H79: =ROUND(F79*G79,2) | J79: =ROUND(K2388,2) | K79: =ROUND(H79-J79,2) | L79: =IF(H79=0,0,K79/H79) | M79: 400W*1200D*2200H | N79: 低压固定柜
A80: =ROW()-ROW(A$6) | B80: T11-AU22、T12-BU22 | C80: 馈线柜 | D80: BlokSeT | E80: 台 | F80: 2 | G80: =ROUND(H2415,2) | H80: =ROUND(F80*G80,2) | J80: =ROUND(K2416,2) | K80: =ROUND(H80-J80,2) | L80: =IF(H80=0,0,K80/H80) | M80: 600W*1200D*2200H | N80: 低压固定柜
A81: =ROW()-ROW(A$6) | B81: T13-AU11、T14-BU11 | C81: 进线柜 | D81: BlokSeT | E81: 台 | F81: 2 | G81: =ROUND(H2449,2) | H81: =ROUND(F81*G81,2) | J81: =ROUND(K2450,2) | K81: =ROUND(H81-J81,2) | L81: =IF(H81=0,0,K81/H81) | M81: 400W*1200D*2200H | N81: 低压固定柜
A82: =ROW()-ROW(A$6) | B82: T13-AU12、T14-BU12 | C82: 馈线柜 | D82: BlokSeT | E82: 台 | F82: 2 | G82: =ROUND(H2479,2) | H82: =ROUND(F82*G82,2) | J82: =ROUND(K2480,2) | K82: =ROUND(H82-J82,2) | L82: =IF(H82=0,0,K82/H82) | M82: 600W*1200D*2200H | N82: 低压固定柜
A83: =ROW()-ROW(A$6) | B83: T13-AU13、T14-BU13 | C83: 馈线柜 | D83: BlokSeT | E83: 台 | F83: 2 | G83: =ROUND(H2509,2) | H83: =ROUND(F83*G83,2) | J83: =ROUND(K2510,2) | K83: =ROUND(H83-J83,2) | L83: =IF(H83=0,0,K83/H83) | M83: 600W*1200D*2200H | N83: 低压固定柜
A84: =ROW()-ROW(A$6) | B84: T1-AU11 | C84: 进线柜 | D84: BlokSeT | E84: 台 | F84: 1 | G84: =ROUND(H2545,2) | H84: =ROUND(F84*G84,2) | J84: =ROUND(K2546,2) | K84: =ROUND(H84-J84,2) | L84: =IF(H84=0,0,K84/H84) | M84: 600W*1200D*2200H | N84: 低压固定柜
A85: =ROW()-ROW(A$6) | B85: T1-AU12 | C85: 馈线柜 | D85: BlokSeT | E85: 台 | F85: 1 | G85: =ROUND(H2579,2) | H85: =ROUND(F85*G85,2) | J85: =ROUND(K2580,2) | K85: =ROUND(H85-J85,2) | L85: =IF(H85=0,0,K85/H85) | M85: 600W*1200D*2200H | N85: 低压固定柜
A86: =ROW()-ROW(A$6) | B86: T2-BU11 | C86: 进线柜 | D86: BlokSeT | E86: 台 | F86: 1 | G86: =ROUND(H2613,2) | H86: =ROUND(F86*G86,2) | J86: =ROUND(K2614,2) | K86: =ROUND(H86-J86,2) | L86: =IF(H86=0,0,K86/H86) | M86: 400W*1200D*2200H | N86: 低压固定柜
A87: =ROW()-ROW(A$6) | B87: T2-BU12 | C87: 馈线柜 | D87: BlokSeT | E87: 台 | F87: 1 | G87: =ROUND(H2644,2) | H87: =ROUND(F87*G87,2) | J87: =ROUND(K2645,2) | K87: =ROUND(H87-J87,2) | L87: =IF(H87=0,0,K87/H87) | M87: 600W*1200D*2200H | N87: 低压固定柜
A88: =ROW()-ROW(A$6) | B88: T3-AU21 | C88: 进线柜 | D88: BlokSeT | E88: 台 | F88: 1 | G88: =ROUND(H2679,2) | H88: =ROUND(F88*G88,2) | J88: =ROUND(K2680,2) | K88: =ROUND(H88-J88,2) | L88: =IF(H88=0,0,K88/H88) | M88: 400W*1200D*2200H | N88: 低压固定柜
A89: =ROW()-ROW(A$6) | B89: T3-AU22 | C89: 馈线柜 | D89: BlokSeT | E89: 台 | F89: 1 | G89: =ROUND(H2713,2) | H89: =ROUND(F89*G89,2) | J89: =ROUND(K2714,2) | K89: =ROUND(H89-J89,2) | L89: =IF(H89=0,0,K89/H89) | M89: 600W*1200D*2200H | N89: 低压固定柜
A90: =ROW()-ROW(A$6) | B90: T6-BU31 | C90: 进线柜 | D90: BlokSeT | E90: 台 | F90: 1 | G90: =ROUND(H2747,2) | H90: =ROUND(F90*G90,2) | J90: =ROUND(K2748,2) | K90: =ROUND(H90-J90,2) | L90: =IF(H90=0,0,K90/H90) | M90: 400W*1200D*2200H | N90: 低压固定柜
A91: =ROW()-ROW(A$6) | B91: T6-BU32 | C91: 馈线柜 | D91: BlokSeT | E91: 台 | F91: 1 | G91: =ROUND(H2779,2) | H91: =ROUND(F91*G91,2) | J91: =ROUND(K2780,2) | K91: =ROUND(H91-J91,2) | L91: =IF(H91=0,0,K91/H91) | M91: 600W*1200D*2200H | N91: 低压固定柜
A92: =ROW()-ROW(A$6) | B92: T10-BU31 | C92: 进线柜 | D92: BlokSeT | E92: 台 | F92: 1 | G92: =ROUND(H2813,2) | H92: =ROUND(F92*G92,2) | J92: =ROUND(K2814,2) | K92: =ROUND(H92-J92,2) | L92: =IF(H92=0,0,K92/H92) | M92: 400W*1200D*2200H | N92: 低压固定柜
A93: =ROW()-ROW(A$6) | B93: T10-BU32 | C93: 馈线柜 | D93: BlokSeT | E93: 台 | F93: 1 | G93: =ROUND(H2847,2) | H93: =ROUND(F93*G93,2) | J93: =ROUND(K2848,2) | K93: =ROUND(H93-J93,2) | L93: =IF(H93=0,0,K93/H93) | M93: 600W*1200D*2200H | N93: 低压固定柜
A94: =ROW()-ROW(A$6) | B94: T11-AU31 | C94: 进线柜 | D94: BlokSeT | E94: 台 | F94: 1 | G94: =ROUND(H2878,2) | H94: =ROUND(F94*G94,2) | J94: =ROUND(K2879,2) | K94: =ROUND(H94-J94,2) | L94: =IF(H94=0,0,K94/H94) | M94: 600W*1200D*2200H | N94: 低压固定柜
A95: =ROW()-ROW(A$6) | B95: T11-AU32 | C95: 馈线柜 | D95: BlokSeT | E95: 台 | F95: 1 | G95: =ROUND(H2910,2) | H95: =ROUND(F95*G95,2) | J95: =ROUND(K2911,2) | K95: =ROUND(H95-J95,2) | L95: =IF(H95=0,0,K95/H95) | M95: 600W*1200D*2200H | N95: 低压固定柜
A96: =ROW()-ROW(A$6) | B96: T13-AU21 | C96: 进线柜 | D96: BlokSeT | E96: 台 | F96: 1 | G96: =ROUND(H2950,2) | H96: =ROUND(F96*G96,2) | J96: =ROUND(K2951,2) | K96: =ROUND(H96-J96,2) | L96: =IF(H96=0,0,K96/H96) | M96: 600W*1200D*2200H | N96: 低压固定柜
A97: =ROW()-ROW(A$6) | B97: T13-AU22 | C97: 进线柜 | D97: BlokSeT | E97: 台 | F97: 1 | G97: =ROUND(H2988,2) | H97: =ROUND(F97*G97,2) | J97: =ROUND(K2989,2) | K97: =ROUND(H97-J97,2) | L97: =IF(H97=0,0,K97/H97) | M97: 600W*1200D*2200H | N97: 低压固定柜
A98: =ROW()-ROW(A$6) | B98: A/B-CHB-01/02 | C98: 双电源切换柜 | D98: BlokSeT | E98: 台 | F98: 4 | G98: =ROUND(H3019,2) | H98: =ROUND(F98*G98,2) | J98: =ROUND(K3020,2) | K98: =ROUND(H98-J98,2) | L98: =IF(H98=0,0,K98/H98) | M98: 900W*1000D*2200H | N98: 低压固定柜
A99: =ROW()-ROW(A$6) | B99: A/B-CHWPB-01/02 | C99: 变频软启柜 | D99: BlokSeT | E99: 台 | F99: 4 | G99: =ROUND(H3056,2) | H99: =ROUND(F99*G99,2) | J99: =ROUND(K3057,2) | K99: =ROUND(H99-J99,2) | L99: =IF(H99=0,0,K99/H99) | M99: 1200W*1000D*2200H | N99: 低压固定柜
A100: =ROW()-ROW(A$6) | B100: A/B-CWPB-01/02 | C100: 变频软启柜 | D100: BlokSeT | E100: 台 | F100: 4 | G100: =ROUND(H3093,2) | H100: =ROUND(F100*G100,2) | J100: =ROUND(K3094,2) | K100: =ROUND(H100-J100,2) | L100: =IF(H100=0,0,K100/H100) | M100: 1200W*1000D*2200H | N100: 低压固定柜
A101: =ROW()-ROW(A$6) | B101: A/B-CTB-01/02 | C101: 变频软启柜 | D101: BlokSeT | E101: 台 | F101: 4 | G101: =ROUND(H3129,2) | H101: =ROUND(F101*G101,2) | J101: =ROUND(K3130,2) | K101: =ROUND(H101-J101,2) | L101: =IF(H101=0,0,K101/H101) | M101: 800W*1000D*2200H | N101: 低压固定柜
...
