Workbook

Sheet 项目信息
A1: =T(B22)
A2: =T(B23)
A4: 工程信息
A5: 项目名称 | B5: 项目C-项目询价：202507-017 | E5: 项目编号
A6: 描述 | E6: 报价交期
A7: 报价单号 | B7: DEMO-QUOTE
A8: 报价人 | B8: 报价员B
A9: 创建日期 | B9: 2025.09.10
A10: 报价审核人
A11: 项目负责人
A12: 项目备注
A13: 客户信息
A14: 客户名称
A15: 联系人
A16: 联系电话
A17: 客户地址
A18: 客户邮编
A19: 客户网址
A20: 客户email
A21: 本企业信息
A22: 单位名称 | B22: 某成套设备有限公司
A23: 英文名称
A24: 联系人 | B24: 宋楠 陆洪标
A25: 联系电话 | B25: 13800000000 13800000000
A26: 销售地区
A27: 分类汇总 金额单位：人民币元
A28: 序号 | B28: 分类名称 | C28: 箱柜数量 | D28: 总 价 | E28: 成本 | F28: 毛利 | G28: 毛利率 | H28: 分类属性
A29: =ROW()-ROW(A$28) | B29: =MID(CELL("filename",folderTable9d0678018b5746038ba7e7e139a5b545),SEARCH({"xlsx]",".xls]"},CELL("filename",folderTable9d0678018b5746038ba7e7e139a5b545))+5,31) | C29: =IF(H29="箱变",标段1!F36,标段1!F32*IF(标段1!F36="",1,标段1!F36)) | D29: =ROUND(标段1!H36,2) | E29: =ROUND(标段1!J36,2) | F29: =ROUND((D29-E29),2) | G29: =IF(D29=0,0,F29/D29) | H29: =IF(OR(ISNUMBER(FIND("箱变",B29))=TRUE,ISNUMBER(FIND("欧变",B29))=TRUE,ISNUMBER(FIND("美变",B29))=TRUE,ISNUMBER(FIND("KVA",UPPER(B29)))=TRUE,ISNUMBER(FIND("箱式变电",B29))=TRUE),"箱变","常规")
A30: =ROW()-ROW(A$28)
A31: =ROW()-ROW(A$28)
A32: =ROW()-ROW(A$28)
A33: =ROW()-ROW(A$28)
A34: =ROW()-ROW(A$28)
A35: =ROW()-ROW(A$28)
A36: =ROW()-ROW(A$28)
A37: =ROW()-ROW(A$28)
A38: =ROW()-ROW(A$28)
A39: =ROW()-ROW(A$28)
A40: =ROW()-ROW(A$28)
A41: =ROW()-ROW(A$28)
... A52: =ROW()-ROW(A$28)
A53: =ROW()-ROW(A$28) | B53: 小计 | C53: =ROUND(SUM(C28:INDEX(C:C,ROW()-1)),2) | D53: =ROUND(SUM(D28:INDEX(D:D,ROW()-1)),2) | E53: =ROUND(SUM(E28:INDEX(E:E,ROW()-1)),2) | F53: =SUM(F28:INDEX(F:F,ROW()-1)) | G53: =IF(D53=0,0,F53/D53) | H53: =SUM(H28:INDEX(H:H,ROW()-1))
A54: =ROW()-ROW(A$28) | B54: 运费 | D54: 0
A55: =ROW()-ROW(A$28) | B55: 合计 | D55: =ROUND(SUM(D53:D54),2)
A56: =ROW()-ROW(A$28) | B56: 人民币大写 | C56: =TEXT(SUBSTITUTE(IF(D55="","",IF(MOD(D55,1)=0,TEXT(INT(D55),"[DBNum2][$-804]G/通用格式元整"),(TEXT(INT(D55),"[DBNum2][$-804]G/通用格式元")&TEXT((INT(D55*10)-INT(D55)*10),"[DBNum2][$-804]G/通用格式角")&TEXT((INT(D55*100)-INT(D55*10)*10),"[DBNum2][$-804]G/通用格式分")))),"零角","零"),)
A57: 报表说明 | B57: 1、包含13%增值税。 2、报价有效期30天。

Sheet 标段1
A2: =T(项目信息!B22)
A3: =T(项目信息!B23)
A4: 成套产品报价清单 金额单位：人民币元
A5: =CONCATENATE("项目名称:",项目信息!B5) | H5: =CONCATENATE("报价序号:",项目信息!B7)
A6: 序号 | B6: 柜号 | C6: 箱柜名称 | D6: 箱柜型号 | E6: 单位 | F6: 数量 | G6: 单 价 | H6: 总 价 | I6: 备注 | J6: 成本总价 | K6: 毛利 | L6: 毛利率 | M6: 箱柜尺寸 | N6: 类别 | O6: 预留 | P6: 预留 | Q6: 图号
A7: =ROW()-ROW(A$6) | B7: 1D1 | C7: 进线柜 | D7: Blokset | E7: 台 | F7: 1 | G7: =ROUND(H74,2) | H7: =ROUND(F7*G7,2) | J7: =ROUND(K75,2) | K7: =ROUND(H7-J7,2) | L7: =IF(H7=0,0,K7/H7) | M7: 1100W*1000D*2200H
A8: =ROW()-ROW(A$6) | B8: 1D2 1D3 2D2 2D3 | C8: 电容柜 | D8: Blokset | E8: 台 | F8: 4 | G8: =ROUND(H108,2) | H8: =ROUND(F8*G8,2) | J8: =ROUND(K109,2) | K8: =ROUND(H8-J8,2) | L8: =IF(H8=0,0,K8/H8) | M8: 1000W*1000D*2200H
A9: =ROW()-ROW(A$6) | B9: 1D4 2D4 | C9: 出线柜 | D9: Blokset | E9: 台 | F9: 2 | G9: =ROUND(H150,2) | H9: =ROUND(F9*G9,2) | J9: =ROUND(K151,2) | K9: =ROUND(H9-J9,2) | L9: =IF(H9=0,0,K9/H9) | M9: 600W*1000D*2200H
A10: =ROW()-ROW(A$6) | B10: 1D5 | C10: 出线柜 | D10: Blokset | E10: 台 | F10: 1 | G10: =ROUND(H188,2) | H10: =ROUND(F10*G10,2) | J10: =ROUND(K189,2) | K10: =ROUND(H10-J10,2) | L10: =IF(H10=0,0,K10/H10) | M10: 600W*1000D*2200H
A11: =ROW()-ROW(A$6) | B11: 1D6 | C11: 出线柜 | D11: Blokset | E11: 台 | F11: 1 | G11: =ROUND(H227,2) | H11: =ROUND(F11*G11,2) | J11: =ROUND(K228,2) | K11: =ROUND(H11-J11,2) | L11: =IF(H11=0,0,K11/H11) | M11: 600W*1000D*2200H
A12: =ROW()-ROW(A$6) | B12: 1D7 | C12: 母联柜 | D12: Blokset | E12: 台 | F12: 1 | G12: =ROUND(H256,2) | H12: =ROUND(F12*G12,2) | J12: =ROUND(K257,2) | K12: =ROUND(H12-J12,2) | L12: =IF(H12=0,0,K12/H12) | M12: 900W*1000D*2200H
A13: =ROW()-ROW(A$6) | B13: 2D6 | C13: 出线柜 | D13: Blokset | E13: 台 | F13: 1 | G13: =ROUND(H297,2) | H13: =ROUND(F13*G13,2) | J13: =ROUND(K298,2) | K13: =ROUND(H13-J13,2) | L13: =IF(H13=0,0,K13/H13) | M13: 600W*1000D*2200H
A14: =ROW()-ROW(A$6) | B14: 2D5 | C14: 出线柜 | D14: Blokset | E14: 台 | F14: 1 | G14: =ROUND(H336,2) | H14: =ROUND(F14*G14,2) | J14: =ROUND(K337,2) | K14: =ROUND(H14-J14,2) | L14: =IF(H14=0,0,K14/H14) | M14: 600W*1000D*2200H
A15: =ROW()-ROW(A$6) | B15: 2D1 | C15: 进线柜 | D15: Blokset | E15: 台 | F15: 1 | G15: =ROUND(H367,2) | H15: =ROUND(F15*G15,2) | J15: =ROUND(K368,2) | K15: =ROUND(H15-J15,2) | L15: =IF(H15=0,0,K15/H15) | M15: 900W*1000D*2200H
A16: =ROW()-ROW(A$6) | B16: 3D1 | C16: 进线柜 | D16: Blokset | E16: 台 | F16: 1 | G16: =ROUND(H403,2) | H16: =ROUND(F16*G16,2) | J16: =ROUND(K404,2) | K16: =ROUND(H16-J16,2) | L16: =IF(H16=0,0,K16/H16) | M16: 700W*1000D*2200H
A17: =ROW()-ROW(A$6) | B17: 3D2 | C17: 电容柜 | D17: Blokset | E17: 台 | F17: 1 | G17: =ROUND(H435,2) | H17: =ROUND(F17*G17,2) | J17: =ROUND(K436,2) | K17: =ROUND(H17-J17,2) | L17: =IF(H17=0,0,K17/H17) | M17: 1000W*1000D*2200H
A18: =ROW()-ROW(A$6) | B18: 3D3 4D3 4D4 | C18: 电容柜 | D18: Blokset | E18: 台 | F18: 3 | G18: =ROUND(H466,2) | H18: =ROUND(F18*G18,2) | J18: =ROUND(K467,2) | K18: =ROUND(H18-J18,2) | L18: =IF(H18=0,0,K18/H18) | M18: 1000W*1000D*2200H
A19: =ROW()-ROW(A$6) | B19: 3D4 4D5 | C19: 出线柜 | D19: Blokset | E19: 台 | F19: 2 | G19: =ROUND(H507,2) | H19: =ROUND(F19*G19,2) | J19: =ROUND(K508,2) | K19: =ROUND(H19-J19,2) | L19: =IF(H19=0,0,K19/H19) | M19: 600W*1000D*2200H
A20: =ROW()-ROW(A$6) | B20: 3D5 4D6 | C20: 出线柜 | D20: Blokset | E20: 台 | F20: 2 | G20: =ROUND(H550,2) | H20: =ROUND(F20*G20,2) | J20: =ROUND(K551,2) | K20: =ROUND(H20-J20,2) | L20: =IF(H20=0,0,K20/H20) | M20: 600W*1000D*2200H
A21: =ROW()-ROW(A$6) | B21: 3D6 4D7 | C21: 出线柜 | D21: Blokset | E21: 台 | F21: 2 | G21: =ROUND(H591,2) | H21: =ROUND(F21*G21,2) | J21: =ROUND(K592,2) | K21: =ROUND(H21-J21,2) | L21: =IF(H21=0,0,K21/H21) | M21: 600W*1000D*2200H
A22: =ROW()-ROW(A$6) | B22: 3D7 | C22: 出线柜 | D22: Blokset | E22: 台 | F22: 1 | G22: =ROUND(H632,2) | H22: =ROUND(F22*G22,2) | J22: =ROUND(K633,2) | K22: =ROUND(H22-J22,2) | L22: =IF(H22=0,0,K22/H22) | M22: 600W*1000D*2200H
A23: =ROW()-ROW(A$6) | B23: 3D8 | C23: 出线柜 | D23: Blokset | E23: 台 | F23: 1 | G23: =ROUND(H676,2) | H23: =ROUND(F23*G23,2) | J23: =ROUND(K677,2) | K23: =ROUND(H23-J23,2) | L23: =IF(H23=0,0,K23/H23) | M23: 800W*1000D*2200H
A24: =ROW()-ROW(A$6) | B24: 3D9 4D10 | C24: 出线柜 | D24: Blokset | E24: 台 | F24: 2 | G24: =ROUND(H720,2) | H24: =ROUND(F24*G24,2) | J24: =ROUND(K721,2) | K24: =ROUND(H24-J24,2) | L24: =IF(H24=0,0,K24/H24) | M24: 800W*1000D*2200H
A25: =ROW()-ROW(A$6) | B25: 3D10 | C25: 出线柜 | D25: Blokset | E25: 台 | F25: 1 | G25: =ROUND(H757,2) | H25: =ROUND(F25*G25,2) | J25: =ROUND(K758,2) | K25: =ROUND(H25-J25,2) | L25: =IF(H25=0,0,K25/H25) | M25: 600W*1000D*2200H
A26: =ROW()-ROW(A$6) | B26: 4D1 | C26: 进线柜 | D26: Blokset | E26: 台 | F26: 1 | G26: =ROUND(H791,2) | H26: =ROUND(F26*G26,2) | J26: =ROUND(K792,2) | K26: =ROUND(H26-J26,2) | L26: =IF(H26=0,0,K26/H26) | M26: 700W*1000D*2200H
A27: =ROW()-ROW(A$6) | B27: 4D2 | C27: 母联柜 | D27: Blokset | E27: 台 | F27: 1 | G27: =ROUND(H823,2) | H27: =ROUND(F27*G27,2) | J27: =ROUND(K824,2) | K27: =ROUND(H27-J27,2) | L27: =IF(H27=0,0,K27/H27) | M27: 700W*1000D*2200H
A28: =ROW()-ROW(A$6) | B28: 4D8 | C28: 出线柜 | D28: Blokset | E28: 台 | F28: 1 | G28: =ROUND(H867,2) | H28: =ROUND(F28*G28,2) | J28: =ROUND(K868,2) | K28: =ROUND(H28-J28,2) | L28: =IF(H28=0,0,K28/H28) | M28: 600W*1000D*2200H
A29: =ROW()-ROW(A$6) | B29: 4D9 | C29: 出线柜 | D29: Blokset | E29: 台 | F29: 1 | G29: =ROUND(H913,2) | H29: =ROUND(F29*G29,2) | J29: =ROUND(K914,2) | K29: =ROUND(H29-J29,2) | L29: =IF(H29=0,0,K29/H29) | M29: 800W*1000D*2200H
A30: =ROW()-ROW(A$6) | B30: 4D11 | C30: 出线柜 | D30: Blokset | E30: 台 | F30: 1 | G30: =ROUND(H953,2) | H30: =ROUND(F30*G30,2) | J30: =ROUND(K954,2) | K30: =ROUND(H30-J30,2) | L30: =IF(H30=0,0,K30/H30) | M30: 600W*1000D*2200H
A31: =ROW()-ROW(A$6)
A32: =ROW()-ROW(A$6) | B32: 小计 | E32: 台 | F32: =SUM(F6:INDEX(F:F,ROW()-1)) | H32: =ROUND(SUM(H6:INDEX(H:H,ROW()-1)),2) | J32: =ROUND(SUM(J6:INDEX(J:J,ROW()-1)),2) | K32: =ROUND(SUM(K6:INDEX(K:K,ROW()-1)),2)
A33: =ROW()-ROW(A$6) | B33: 包装费 | E33: 台 | F33: 34 | G33: 100 | H33: =ROUND(F33*G33,2) | J33: =ROUND(H33,2)
A34: =ROW()-ROW(A$6) | B34: 运输费 | E34: 套 | F34: 1 | G34: 5800 | H34: =ROUND(F34*G34,2) | J34: =ROUND(H34,2)
A35: =ROW()-ROW(A$6) | B35: 运载工具车 | E35: 台 | F35: 1 | G35: 0 | H35: =ROUND(F35*G35,2) | J35: =ROUND(H35,2)
A36: =ROW()-ROW(A$6) | B36: 合计(人民币大写) | C36: =TEXT(SUBSTITUTE(IF(H36="","",IF(MOD(H36,1)=0,TEXT(INT(H36),"[DBNum2][$-804]G/通用格式元整"),(TEXT(INT(H36),"[DBNum2][$-804]G/通用格式元")&TEXT((INT(H36*10)-INT(H36)*10),"[DBNum2][$-804]G/通用格式角")&TEXT((INT(H36*100)-INT(H36*10)*10),"[DBNum2][$-804]G/通用格式分")))),"零角","零"),) | F36: =IF(项目信息!H29="箱变",1,"") | G36: =ROUND(SUM(H32:H35),2) | H36: =ROUND(IF(F36="",1,F36)*G36,2) | J36: =ROUND(IF(F36="",1,F36)*SUM(J32:J35),2) | K36: =ROUND(IF(F36="",1,F36)*SUM(K32:K35),2) | L36: =IF(H36=0,0,K36/H36) | R36: 17.71 | S36: =ROUND(R36*H36,0)
A37: 说明
A41: =CONCATENATE("报价人：",项目信息!B8) | H41: =项目信息!B9
A42: =T(项目信息!$B$22)
A43: =T(项目信息!$B$23)
A44: 成套产品报价明细表
A45: 柜号: | B45: 1D1 | C45: 型号: | D45: Blokset | F45: 名称: | G45: 进线柜 | J45: 箱柜尺寸: | K45: 1100W*1000D*2200H | L45: 类别:
A46: 序号 | B46: 元件名称 | C46: 型号规格 | D46: 生产厂家 | E46: 单位 | F46: 数量 | G46: 单 价 | H46: 总 价 | I46: 备注 | J46: 成本单价 | K46: 成本总价 | L46: 报出 系数 | M46: 表价 | N46: 折扣 系数 | O46: 取费 系数 | P46: 成套费 | Q46: 类别 | R46: 物料编码 | S46: 产地 | T46: 加工费 | U46: 订货号 | V46: 人工 | W46: 辅料
A47: =ROW()-ROW(A$46) | B47: 双电源自动转换开关 | C47: WTS-4000/2500/4DL | D47: 甲供/施耐德万高 | E47: 只 | F47: 1 | G47: =IF(AND(B47="",C47=""),"",ROUND(M47*L47*N47,2)) | H47: =IF(AND(B47="",C47=""),"",ROUND(F47*G47,2)) | J47: =IF(AND(B47="",C47=""),"",ROUND(M47*N47,2)) | K47: =IF(AND(B47="",C47=""),"",ROUND(J47*F47,2)) | L47: 1 | M47: 117651 | N47: 0 | O47: {=IF(AND(B47="",C47=""),"",IF(G47>=20000,0.05,IF(G47>=10000,0.1,IF(G47>=5000,0.2,IF(G47>=1000,0.3,IF(G47>=0,0.4,{0}))))))} | P47: =IF(AND(B47="",C47=""),"",ROUND(H47*O47,2)) | Q47: 元件 | T47: 0 | U47: TW4AD4L25H4TPG
A48: =ROW()-ROW(A$46) | B48: 双电源开关ATMT | C48: ATMT25 H1 4P MIC5.0E 带通讯 | D48: 甲供/施耐德万高 | E48: 套 | F48: 0.33 | G48: =IF(AND(B48="",C48=""),"",ROUND(M48*L48*N48,2)) | H48: =IF(AND(B48="",C48=""),"",ROUND(F48*G48,2)) | J48: =IF(AND(B48="",C48=""),"",ROUND(M48*N48,2)) | K48: =IF(AND(B48="",C48=""),"",ROUND(J48*F48,2)) | L48: 1 | M48: 1e-07 | N48: 0 | O48: {=IF(AND(B48="",C48=""),"",IF(G48>=20000,0.05,IF(G48>=10000,0.1,IF(G48>=5000,0.2,IF(G48>=1000,0.3,IF(G48>=0,0.4,{0}))))))} | P48: =IF(AND(B48="",C48=""),"",ROUND(H48*O48,2)) | Q48: 元件 | T48: 0
A49: =ROW()-ROW(A$46) | B49: 测量电流互感器 | C49: SD-0.66-100II-C 2500/5 | D49: 杭州桑迪 | E49: 只 | F49: 6 | G49: =IF(AND(B49="",C49=""),"",ROUND(M49*L49*N49,2)) | H49: =IF(AND(B49="",C49=""),"",ROUND(F49*G49,2)) | J49: =IF(AND(B49="",C49=""),"",ROUND(M49*N49,2)) | K49: =IF(AND(B49="",C49=""),"",ROUND(J49*F49,2)) | L49: 1 | M49: 161.85 | N49: 1 | O49: {=IF(AND(B49="",C49=""),"",IF(G49>=20000,0.05,IF(G49>=10000,0.1,IF(G49>=5000,0.2,IF(G49>=1000,0.3,IF(G49>=0,0.4,{0}))))))} | P49: =IF(AND(B49="",C49=""),"",ROUND(H49*O49,2)) | Q49: 元件 | T49: 0
A50: =ROW()-ROW(A$46) | B50: 多功能表 | C50: PM4633 | D50: 甲供/施耐德电气 | E50: 只 | F50: =IF(AND(B50="",C50=""),"",1) | G50: =IF(AND(B50="",C50=""),"",ROUND(M50*L50*N50,2)) | H50: =IF(AND(B50="",C50=""),"",ROUND(F50*G50,2)) | J50: =IF(AND(B50="",C50=""),"",ROUND(M50*N50,2)) | K50: =IF(AND(B50="",C50=""),"",ROUND(J50*F50,2)) | L50: 1 | M50: 1e-07 | N50: 0 | O50: {=IF(AND(B50="",C50=""),"",IF(G50>=20000,0.05,IF(G50>=10000,0.1,IF(G50>=5000,0.2,IF(G50>=1000,0.3,IF(G50>=0,0.4,{0}))))))} | P50: =IF(AND(B50="",C50=""),"",ROUND(H50*O50,2)) | Q50: 元件 | T50: 0
A51: =ROW()-ROW(A$46) | B51: SPD断路器 | C51: iSCB1 25L1 4P | D51: 甲供/施耐德万高 | E51: 只 | F51: =IF(AND(B51="",C51=""),"",1) | G51: =IF(AND(B51="",C51=""),"",ROUND(M51*L51*N51,2)) | H51: =IF(AND(B51="",C51=""),"",ROUND(F51*G51,2)) | J51: =IF(AND(B51="",C51=""),"",ROUND(M51*N51,2)) | K51: =IF(AND(B51="",C51=""),"",ROUND(J51*F51,2)) | L51: 1 | M51: 1e-07 | N51: 0 | O51: {=IF(AND(B51="",C51=""),"",IF(G51>=20000,0.05,IF(G51>=10000,0.1,IF(G51>=5000,0.2,IF(G51>=1000,0.3,IF(G51>=0,0.4,{0}))))))} | P51: =IF(AND(B51="",C51=""),"",ROUND(H51*O51,2)) | Q51: 元件 | T51: 0
A52: =ROW()-ROW(A$46) | B52: 浪涌保护器 | C52: iPRF1 12.5r 3P+N | D52: 甲供/施耐德万高 | E52: 只 | F52: =IF(AND(B52="",C52=""),"",1) | G52: =IF(AND(B52="",C52=""),"",ROUND(M52*L52*N52,2)) | H52: =IF(AND(B52="",C52=""),"",ROUND(F52*G52,2)) | J52: =IF(AND(B52="",C52=""),"",ROUND(M52*N52,2)) | K52: =IF(AND(B52="",C52=""),"",ROUND(J52*F52,2)) | L52: 1 | M52: 1e-07 | N52: 0 | O52: {=IF(AND(B52="",C52=""),"",IF(G52>=20000,0.05,IF(G52>=10000,0.1,IF(G52>=5000,0.2,IF(G52>=1000,0.3,IF(G52>=0,0.4,{0}))))))} | P52: =IF(AND(B52="",C52=""),"",ROUND(H52*O52,2)) | Q52: 元件 | T52: 0
A53: =ROW()-ROW(A$46) | B53: SP元件 | C53: 智能网关 PAS700 | D53: 甲供/施耐德电气 | E53: 只 | F53: =IF(AND(B53="",C53=""),"",1) | G53: =IF(AND(B53="",C53=""),"",ROUND(M53*L53*N53,2)) | H53: =IF(AND(B53="",C53=""),"",ROUND(F53*G53,2)) | J53: =IF(AND(B53="",C53=""),"",ROUND(M53*N53,2)) | K53: =IF(AND(B53="",C53=""),"",ROUND(J53*F53,2)) | L53: 1 | M53: 1e-07 | N53: 0 | O53: {=IF(AND(B53="",C53=""),"",IF(G53>=20000,0.05,IF(G53>=10000,0.1,IF(G53>=5000,0.2,IF(G53>=1000,0.3,IF(G53>=0,0.4,{0}))))))} | P53: =IF(AND(B53="",C53=""),"",ROUND(H53*O53,2)) | Q53: 元件 | T53: 0
A54: =ROW()-ROW(A$46) | B54: SP元件 | C54: POI 站控专家 软件 | D54: 甲供/施耐德电气 | E54: 只 | F54: =IF(AND(B54="",C54=""),"",1) | G54: =IF(AND(B54="",C54=""),"",ROUND(M54*L54*N54,2)) | H54: =IF(AND(B54="",C54=""),"",ROUND(F54*G54,2)) | J54: =IF(AND(B54="",C54=""),"",ROUND(M54*N54,2)) | K54: =IF(AND(B54="",C54=""),"",ROUND(J54*F54,2)) | L54: 1 | M54: 1e-07 | N54: 0 | O54: {=IF(AND(B54="",C54=""),"",IF(G54>=20000,0.05,IF(G54>=10000,0.1,IF(G54>=5000,0.2,IF(G54>=1000,0.3,IF(G54>=0,0.4,{0}))))))} | P54: =IF(AND(B54="",C54=""),"",ROUND(H54*O54,2)) | Q54: 元件 | T54: 0
A55: =ROW()-ROW(A$46) | B55: SP元件 | C55: POI 站控专家 硬件 | D55: 甲供/施耐德电气 | E55: 只 | F55: =IF(AND(B55="",C55=""),"",1) | G55: =IF(AND(B55="",C55=""),"",ROUND(M55*L55*N55,2)) | H55: =IF(AND(B55="",C55=""),"",ROUND(F55*G55,2)) | J55: =IF(AND(B55="",C55=""),"",ROUND(M55*N55,2)) | K55: =IF(AND(B55="",C55=""),"",ROUND(J55*F55,2)) | L55: 1 | M55: 1e-07 | N55: 0 | O55: {=IF(AND(B55="",C55=""),"",IF(G55>=20000,0.05,IF(G55>=10000,0.1,IF(G55>=5000,0.2,IF(G55>=1000,0.3,IF(G55>=0,0.4,{0}))))))} | P55: =IF(AND(B55="",C55=""),"",ROUND(H55*O55,2)) | Q55: 元件 | T55: 0
A56: =ROW()-ROW(A$46) | B56: 指示灯 | C56: XA2EVM3LC | D56: 施耐德电气 | E56: 只 | F56: 1 | G56: =IF(AND(B56="",C56=""),"",ROUND(M56*L56*N56,2)) | H56: =IF(AND(B56="",C56=""),"",ROUND(F56*G56,2)) | J56: =IF(AND(B56="",C56=""),"",ROUND(M56*N56,2)) | K56: =IF(AND(B56="",C56=""),"",ROUND(J56*F56,2)) | L56: 1 | M56: 16.43 | N56: 0.5 | O56: {=IF(AND(B56="",C56=""),"",IF(G56>=20000,0.05,IF(G56>=10000,0.1,IF(G56>=5000,0.2,IF(G56>=1000,0.3,IF(G56>=0,0.4,{0}))))))} | P56: =IF(AND(B56="",C56=""),"",ROUND(H56*O56,2)) | Q56: 元件 | T56: 0 | U56: XA2EVM3LC
A57: =ROW()-ROW(A$46) | B57: 指示灯 | C57: XA2EVM4LC | D57: 施耐德电气 | E57: 只 | F57: 1 | G57: =IF(AND(B57="",C57=""),"",ROUND(M57*L57*N57,2)) | H57: =IF(AND(B57="",C57=""),"",ROUND(F57*G57,2)) | J57: =IF(AND(B57="",C57=""),"",ROUND(M57*N57,2)) | K57: =IF(AND(B57="",C57=""),"",ROUND(J57*F57,2)) | L57: 1 | M57: 16.43 | N57: 0.5 | O57: {=IF(AND(B57="",C57=""),"",IF(G57>=20000,0.05,IF(G57>=10000,0.1,IF(G57>=5000,0.2,IF(G57>=1000,0.3,IF(G57>=0,0.4,{0}))))))} | P57: =IF(AND(B57="",C57=""),"",ROUND(H57*O57,2)) | Q57: 元件 | T57: 0 | U57: XA2EVM4LC
A58: =ROW()-ROW(A$46) | B58: 指示灯 | C58: XA2EVM5LC | D58: 施耐德电气 | E58: 只 | F58: 1 | G58: =IF(AND(B58="",C58=""),"",ROUND(M58*L58*N58,2)) | H58: =IF(AND(B58="",C58=""),"",ROUND(F58*G58,2)) | J58: =IF(AND(B58="",C58=""),"",ROUND(M58*N58,2)) | K58: =IF(AND(B58="",C58=""),"",ROUND(J58*F58,2)) | L58: 1 | M58: 16.43 | N58: 0.5 | O58: {=IF(AND(B58="",C58=""),"",IF(G58>=20000,0.05,IF(G58>=10000,0.1,IF(G58>=5000,0.2,IF(G58>=1000,0.3,IF(G58>=0,0.4,{0}))))))} | P58: =IF(AND(B58="",C58=""),"",ROUND(H58*O58,2)) | Q58: 元件 | T58: 0 | U58: XA2EVM5LC
A59: =ROW()-ROW(A$46) | B59: 按钮 | C59: XA2EA31 | D59: 施耐德电气 | E59: 只 | F59: 1 | G59: =IF(AND(B59="",C59=""),"",ROUND(M59*L59*N59,2)) | H59: =IF(AND(B59="",C59=""),"",ROUND(F59*G59,2)) | J59: =IF(AND(B59="",C59=""),"",ROUND(M59*N59,2)) | K59: =IF(AND(B59="",C59=""),"",ROUND(J59*F59,2)) | L59: 1 | M59: 15.55 | N59: 0.5 | O59: {=IF(AND(B59="",C59=""),"",IF(G59>=20000,0.05,IF(G59>=10000,0.1,IF(G59>=5000,0.2,IF(G59>=1000,0.3,IF(G59>=0,0.4,{0}))))))} | P59: =IF(AND(B59="",C59=""),"",ROUND(H59*O59,2)) | Q59: 元件 | T59: 0 | U59: XA2EA31
A60: =ROW()-ROW(A$46) | B60: 按钮 | C60: XA2EA41 | D60: 施耐德电气 | E60: 只 | F60: 1 | G60: =IF(AND(B60="",C60=""),"",ROUND(M60*L60*N60,2)) | H60: =IF(AND(B60="",C60=""),"",ROUND(F60*G60,2)) | J60: =IF(AND(B60="",C60=""),"",ROUND(M60*N60,2)) | K60: =IF(AND(B60="",C60=""),"",ROUND(J60*F60,2)) | L60: 1 | M60: 15.55 | N60: 0.5 | O60: {=IF(AND(B60="",C60=""),"",IF(G60>=20000,0.05,IF(G60>=10000,0.1,IF(G60>=5000,0.2,IF(G60>=1000,0.3,IF(G60>=0,0.4,{0}))))))} | P60: =IF(AND(B60="",C60=""),"",ROUND(H60*O60,2)) | Q60: 元件 | T60: 0 | U60: XA2EA41
A61: =ROW()-ROW(A$46) | B61: 熔断器 | C61: UK5-HESI | D61: 菲尼克斯 | E61: 只 | F61: 4 | G61: =IF(AND(B61="",C61=""),"",ROUND(M61*L61*N61,2)) | H61: =IF(AND(B61="",C61=""),"",ROUND(F61*G61,2)) | J61: =IF(AND(B61="",C61=""),"",ROUND(M61*N61,2)) | K61: =IF(AND(B61="",C61=""),"",ROUND(J61*F61,2)) | L61: 1 | M61: 7 | N61: 1 | O61: {=IF(AND(B61="",C61=""),"",IF(G61>=20000,0.05,IF(G61>=10000,0.1,IF(G61>=5000,0.2,IF(G61>=1000,0.3,IF(G61>=0,0.4,{0}))))))} | P61: =IF(AND(B61="",C61=""),"",ROUND(H61*O61,2)) | Q61: 元件 | T61: 0
A62: =ROW()-ROW(A$46) | B62: 水平排2500A | C62: TMY 3*(2*125*5)+1*125*5+2*50*5 | D62: 国产优质 | E62: 米 | F62: 1.1 | G62: =IF(AND(B62="",C62=""),"",ROUND(M62*L62*N62,2)) | H62: =IF(AND(B62="",C62=""),"",ROUND(F62*G62,2)) | J62: =IF(AND(B62="",C62=""),"",ROUND(M62*N62,2)) | K62: =IF(AND(B62="",C62=""),"",ROUND(J62*F62,2)) | L62: 1 | M62: 3633.9201 | N62: 1 | O62: {=IF(AND(B62="",C62=""),"",IF(G62>=20000,0.05,IF(G62>=10000,0.1,IF(G62>=5000,0.2,IF(G62>=1000,0.3,IF(G62>=0,0.4,{0}))))))} | P62: =IF(AND(B62="",C62=""),"",ROUND(H62*O62,2)) | Q62: 母排 | T62: 0
A63: =ROW()-ROW(A$46) | B63: WTS电源侧 | C63: TMY 4*（4*100*5） | D63: 国产优质 | E63: 米 | F63: =0.8+1.8 | G63: =IF(AND(B63="",C63=""),"",ROUND(M63*L63*N63,2)) | H63: =IF(AND(B63="",C63=""),"",ROUND(F63*G63,2)) | J63: =IF(AND(B63="",C63=""),"",ROUND(M63*N63,2)) | K63: =IF(AND(B63="",C63=""),"",ROUND(J63*F63,2)) | L63: 1 | M63: 5963.356 | N63: 1 | O63: {=IF(AND(B63="",C63=""),"",IF(G63>=20000,0.05,IF(G63>=10000,0.1,IF(G63>=5000,0.2,IF(G63>=1000,0.3,IF(G63>=0,0.4,{0}))))))} | P63: =IF(AND(B63="",C63=""),"",ROUND(H63*O63,2)) | Q63: 母排 | T63: 0
A64: =ROW()-ROW(A$46) | B64: WTS负载侧 | C64: TMY 4*（4*100*5） | D64: 国产优质 | E64: 米 | F64: 1.8 | G64: =IF(AND(B64="",C64=""),"",ROUND(M64*L64*N64,2)) | H64: =IF(AND(B64="",C64=""),"",ROUND(F64*G64,2)) | J64: =IF(AND(B64="",C64=""),"",ROUND(M64*N64,2)) | K64: =IF(AND(B64="",C64=""),"",ROUND(J64*F64,2)) | L64: 1 | M64: 5963.356 | N64: 1 | O64: {=IF(AND(B64="",C64=""),"",IF(G64>=20000,0.05,IF(G64>=10000,0.1,IF(G64>=5000,0.2,IF(G64>=1000,0.3,IF(G64>=0,0.4,{0}))))))} | P64: =IF(AND(B64="",C64=""),"",ROUND(H64*O64,2)) | Q64: 母排 | T64: 0
A65: =ROW()-ROW(A$46) | B65: MT25上桩头 | C65: TMY 4*（4*80*5） | D65: 国产优质 | E65: 米 | F65: 0.65 | G65: =IF(AND(B65="",C65=""),"",ROUND(M65*L65*N65,2)) | H65: =IF(AND(B65="",C65=""),"",ROUND(F65*G65,2)) | J65: =IF(AND(B65="",C65=""),"",ROUND(M65*N65,2)) | K65: =IF(AND(B65="",C65=""),"",ROUND(J65*F65,2)) | L65: 1 | M65: 4770.6848 | N65: 1 | O65: {=IF(AND(B65="",C65=""),"",IF(G65>=20000,0.05,IF(G65>=10000,0.1,IF(G65>=5000,0.2,IF(G65>=1000,0.3,IF(G65>=0,0.4,{0}))))))} | P65: =IF(AND(B65="",C65=""),"",ROUND(H65*O65,2)) | Q65: 母排 | T65: 0
A66: =ROW()-ROW(A$46) | B66: MT25下桩头 | C66: TMY 4*（4*80*5） | D66: 国产优质 | E66: 米 | F66: 4 | G66: =IF(AND(B66="",C66=""),"",ROUND(M66*L66*N66,2)) | H66: =IF(AND(B66="",C66=""),"",ROUND(F66*G66,2)) | J66: =IF(AND(B66="",C66=""),"",ROUND(M66*N66,2)) | K66: =IF(AND(B66="",C66=""),"",ROUND(J66*F66,2)) | L66: 1 | M66: 4770.6848 | N66: 1 | O66: {=IF(AND(B66="",C66=""),"",IF(G66>=20000,0.05,IF(G66>=10000,0.1,IF(G66>=5000,0.2,IF(G66>=1000,0.3,IF(G66>=0,0.4,{0}))))))} | P66: =IF(AND(B66="",C66=""),"",ROUND(H66*O66,2)) | Q66: 母排 | T66: 0
A67: =ROW()-ROW(A$46) | B67: 导线及辅料 | D67: 国产优质 | E67: 套 | F67: 1 | G67: =IF(AND(B67="",C67=""),"",ROUND(M67*L67*N67,2)) | H67: =IF(AND(B67="",C67=""),"",ROUND(F67*G67,2)) | J67: =IF(AND(B67="",C67=""),"",ROUND(M67*N67,2)) | K67: =IF(AND(B67="",C67=""),"",ROUND(J67*F67,2)) | L67: 1 | M67: 1000 | N67: 1 | O67: {=IF(AND(B67="",C67=""),"",IF(G67>=20000,0.05,IF(G67>=10000,0.1,IF(G67>=5000,0.2,IF(G67>=1000,0.3,IF(G67>=0,0.4,{0}))))))} | P67: =IF(AND(B67="",C67=""),"",ROUND(H67*O67,2)) | Q67: 辅料 | T67: 0
A68: =ROW()-ROW(A$46) | B68: Blokset柜 | C68: 1100W*1000D*2200H | D68: 清科 | E68: 台 | F68: 1 | G68: =IF(AND(B68="",C68=""),"",ROUND(M68*L68*N68,2)) | H68: =IF(AND(B68="",C68=""),"",ROUND(F68*G68,2)) | J68: =IF(AND(B68="",C68=""),"",ROUND(M68*N68,2)) | K68: =IF(AND(B68="",C68=""),"",ROUND(J68*F68,2)) | L68: 1 | M68: 5609 | N68: 1 | O68: {=IF(AND(B68="",C68=""),"",IF(G68>=20000,0.05,IF(G68>=10000,0.1,IF(G68>=5000,0.2,IF(G68>=1000,0.3,IF(G68>=0,0.4,{0}))))))} | P68: =IF(AND(B68="",C68=""),"",ROUND(H68*O68,2)) | Q68: 箱体 | T68: 0
A69: =ROW()-ROW(A$46) | F69: =IF(AND(B69="",C69=""),"",1) | G69: =IF(AND(B69="",C69=""),"",ROUND(M69*L69*N69,2)) | H69: =IF(AND(B69="",C69=""),"",ROUND(F69*G69,2)) | J69: =IF(AND(B69="",C69=""),"",ROUND(M69*N69,2)) | K69: =IF(AND(B69="",C69=""),"",ROUND(J69*F69,2)) | L69: =IF(AND(B69="",C69=""),"",1) | N69: =IF(AND(B69="",C69=""),"",1) | O69: {=IF(AND(B69="",C69=""),"",IF(G69>=20000,0.05,IF(G69>=10000,0.1,IF(G69>=5000,0.2,IF(G69>=1000,0.3,IF(G69>=0,0.4,{0}))))))} | P69: =IF(AND(B69="",C69=""),"",ROUND(H69*O69,2)) | Q69: =IF(AND(B69="",C69=""),"","元件")
A70: =ROW()-ROW(A$46) | F70: =IF(AND(B70="",C70=""),"",1) | G70: =IF(AND(B70="",C70=""),"",ROUND(M70*L70*N70,2)) | H70: =IF(AND(B70="",C70=""),"",ROUND(F70*G70,2)) | J70: =IF(AND(B70="",C70=""),"",ROUND(M70*N70,2)) | K70: =IF(AND(B70="",C70=""),"",ROUND(J70*F70,2)) | L70: =IF(AND(B70="",C70=""),"",1) | N70: =IF(AND(B70="",C70=""),"",1) | O70: {=IF(AND(B70="",C70=""),"",IF(G70>=20000,0.05,IF(G70>=10000,0.1,IF(G70>=5000,0.2,IF(G70>=1000,0.3,IF(G70>=0,0.4,{0}))))))} | P70: =IF(AND(B70="",C70=""),"",ROUND(H70*O70,2)) | Q70: =IF(AND(B70="",C70=""),"","元件")
A71: =ROW()-ROW(A$46) | B71: 小计 | H71: =ROUND(SUM(H46:INDEX(H:H,ROW()-1)),2) | K71: =ROUND(SUM(K46:INDEX(K:K,ROW()-1)),2) | V71: {=ROUND(SUMPRODUCT(F46:INDEX(F:F,ROW()-1),V46:INDEX(V:V,ROW()-1)),2)} | W71: {=ROUND(SUMPRODUCT(F46:INDEX(F:F,ROW()-1),W46:INDEX(W:W,ROW()-1)),2)}
A72: =ROW()-ROW(A$46) | B72: 成套费 | H72: 944.76 | K72: 944.76
A73: =ROW()-ROW(A$46) | H73: 17.26
A74: =ROW()-ROW(A$46) | B74: 单台合计 | H74: =ROUND(SUM(H71:H72),2) | K74: =ROUND(SUM(K71:K72),2)
A75: 总计 | E75: 台 | F75: 1 | G75: =ROUND(H74,2) | H75: =ROUND(F75*G75,2) | K75: =ROUND(K74*F75,2)
A78: =CONCATENATE("报价人：",项目信息!$B$8) | H78: =项目信息!$B$9
A79: =T(项目信息!$B$22)
A80: =T(项目信息!$B$23)
A81: 成套产品报价明细表
A82: 柜号: | B82: 1D2 1D3 2D2 2D3 | C82: 型号: | D82: Blokset | F82: 名称: | G82: 电容柜 | J82: 箱柜尺寸: | K82: 1000W*1000D*2200H | L82: 类别:
A83: 序号 | B83: 元件名称 | C83: 型号规格 | D83: 生产厂家 | E83: 单位 | F83: 数量 | G83: 单 价 | H83: 总 价 | I83: 备注 | J83: 成本单价 | K83: 成本总价 | L83: 报出 系数 | M83: 表价 | N83: 折扣 系数 | O83: 取费 系数 | P83: 成套费 | Q83: 类别 | R83: 物料编码 | S83: 产地 | T83: 加工费 | U83: 订货号 | V83: 人工 | W83: 辅料
A84: =ROW()-ROW(A$83) | B84: 交流塑壳断路器 | C84: NSX630N MIC 2.3 630 3P P | D84: 甲供/施耐德电气 | E84: 只 | F84: 1 | G84: =IF(AND(B84="",C84=""),"",ROUND(M84*L84*N84,2)) | H84: =IF(AND(B84="",C84=""),"",ROUND(F84*G84,2)) | J84: =IF(AND(B84="",C84=""),"",ROUND(M84*N84,2)) | K84: =IF(AND(B84="",C84=""),"",ROUND(J84*F84,2)) | L84: 1 | M84: 7668.45 | N84: 0 | O84: {=IF(AND(B84="",C84=""),"",IF(G84>=20000,0.05,IF(G84>=10000,0.1,IF(G84>=5000,0.2,IF(G84>=1000,0.3,IF(G84>=0,0.4,{0}))))))} | P84: =IF(AND(B84="",C84=""),"",ROUND(H84*O84,2)) | Q84: 元件 | T84: 0 | U84: C63N32D630P | X84: NSX630N MIC 5.3B 630 3P P
A85: =ROW()-ROW(A$83) | B85: 新外观延伸旋转手柄 | C85: 标准延伸旋转手柄/新外观延伸旋转手柄 400/630A | D85: 甲供/施耐德电气 | E85: 只 | F85: 1 | G85: =IF(AND(B85="",C85=""),"",ROUND(M85*L85*N85,2)) | H85: =IF(AND(B85="",C85=""),"",ROUND(F85*G85,2)) | J85: =IF(AND(B85="",C85=""),"",ROUND(M85*N85,2)) | K85: =IF(AND(B85="",C85=""),"",ROUND(J85*F85,2)) | L85: 1 | M85: 270.62 | N85: 0 | O85: {=IF(AND(B85="",C85=""),"",IF(G85>=20000,0.05,IF(G85>=10000,0.1,IF(G85>=5000,0.2,IF(G85>=1000,0.3,IF(G85>=0,0.4,{0}))))))} | P85: =IF(AND(B85="",C85=""),"",ROUND(H85*O85,2)) | Q85: 元件 | T85: 0 | U85: LV432598T
A86: =ROW()-ROW(A$83) | B86: 测量电流互感器 | C86: SD-0.66-60II-C 600/5A | D86: 杭州桑迪 | E86: 只 | F86: 3 | G86: =IF(AND(B86="",C86=""),"",ROUND(M86*L86*N86,2)) | H86: =IF(AND(B86="",C86=""),"",ROUND(F86*G86,2)) | J86: =IF(AND(B86="",C86=""),"",ROUND(M86*N86,2)) | K86: =IF(AND(B86="",C86=""),"",ROUND(J86*F86,2)) | L86: 1 | M86: 76.7 | N86: 1 | O86: {=IF(AND(B86="",C86=""),"",IF(G86>=20000,0.05,IF(G86>=10000,0.1,IF(G86>=5000,0.2,IF(G86>=1000,0.3,IF(G86>=0,0.4,{0}))))))} | P86: =IF(AND(B86="",C86=""),"",ROUND(H86*O86,2)) | Q86: 元件 | T86: 0
A87: =ROW()-ROW(A$83) | B87: 多功能表 | C87: PM4101 | D87: 甲供/施耐德电气 | E87: 只 | F87: =IF(AND(B87="",C87=""),"",1) | G87: =IF(AND(B87="",C87=""),"",ROUND(M87*L87*N87,2)) | H87: =IF(AND(B87="",C87=""),"",ROUND(F87*G87,2)) | J87: =IF(AND(B87="",C87=""),"",ROUND(M87*N87,2)) | K87: =IF(AND(B87="",C87=""),"",ROUND(J87*F87,2)) | L87: 1 | M87: 1e-07 | N87: 0 | O87: {=IF(AND(B87="",C87=""),"",IF(G87>=20000,0.05,IF(G87>=10000,0.1,IF(G87>=5000,0.2,IF(G87>=1000,0.3,IF(G87>=0,0.4,{0}))))))} | P87: =IF(AND(B87="",C87=""),"",ROUND(H87*O87,2)) | Q87: 元件 | T87: 0
A88: =ROW()-ROW(A$83) | B88: 晶闸管投切开关 | C88: NTHY30A40 30kvar 3P 50Hz 400V | D88: 甲供/施耐德电气 | E88: 只 | F88: 2 | G88: =IF(AND(B88="",C88=""),"",ROUND(M88*L88*N88,2)) | H88: =IF(AND(B88="",C88=""),"",ROUND(F88*G88,2)) | J88: =IF(AND(B88="",C88=""),"",ROUND(M88*N88,2)) | K88: =IF(AND(B88="",C88=""),"",ROUND(J88*F88,2)) | L88: 1 | M88: 1e-07 | N88: 0 | O88: {=IF(AND(B88="",C88=""),"",IF(G88>=20000,0.05,IF(G88>=10000,0.1,IF(G88>=5000,0.2,IF(G88>=1000,0.3,IF(G88>=0,0.4,{0}))))))} | P88: =IF(AND(B88="",C88=""),"",ROUND(H88*O88,2)) | Q88: 元件 | T88: 0
A89: =ROW()-ROW(A$83) | B89: 晶闸管投切开关 | C89: NTHY50A40 50kvar 3P 50Hz 400V | D89: 甲供/施耐德电气 | E89: 只 | F89: 3 | G89: =IF(AND(B89="",C89=""),"",ROUND(M89*L89*N89,2)) | H89: =IF(AND(B89="",C89=""),"",ROUND(F89*G89,2)) | J89: =IF(AND(B89="",C89=""),"",ROUND(M89*N89,2)) | K89: =IF(AND(B89="",C89=""),"",ROUND(J89*F89,2)) | L89: 1 | M89: 1e-07 | N89: 0 | O89: {=IF(AND(B89="",C89=""),"",IF(G89>=20000,0.05,IF(G89>=10000,0.1,IF(G89>=5000,0.2,IF(G89>=1000,0.3,IF(G89>=0,0.4,{0}))))))} | P89: =IF(AND(B89="",C89=""),"",ROUND(H89*O89,2)) | Q89: 元件 | T89: 0
A90: =ROW()-ROW(A$83) | B90: 电容器 | C90: Can SDY 25 kvar -7% | D90: 甲供/施耐德电气 | E90: 只 | F90: 8 | G90: =IF(AND(B90="",C90=""),"",ROUND(M90*L90*N90,2)) | H90: =IF(AND(B90="",C90=""),"",ROUND(F90*G90,2)) | J90: =IF(AND(B90="",C90=""),"",ROUND(M90*N90,2)) | K90: =IF(AND(B90="",C90=""),"",ROUND(J90*F90,2)) | L90: 1 | M90: 1e-07 | N90: 0 | O90: {=IF(AND(B90="",C90=""),"",IF(G90>=20000,0.05,IF(G90>=10000,0.1,IF(G90>=5000,0.2,IF(G90>=1000,0.3,IF(G90>=0,0.4,{0}))))))} | P90: =IF(AND(B90="",C90=""),"",ROUND(H90*O90,2)) | Q90: 元件 | T90: 0
A91: =ROW()-ROW(A$83) | B91: 电抗器 | C91: LVR 7% 25Kvar 400V/50Hz | D91: 甲供/施耐德电气 | E91: 只 | F91: 2 | G91: =IF(AND(B91="",C91=""),"",ROUND(M91*L91*N91,2)) | H91: =IF(AND(B91="",C91=""),"",ROUND(F91*G91,2)) | J91: =IF(AND(B91="",C91=""),"",ROUND(M91*N91,2)) | K91: =IF(AND(B91="",C91=""),"",ROUND(J91*F91,2)) | L91: 1 | M91: 1e-07 | N91: 0 | O91: {=IF(AND(B91="",C91=""),"",IF(G91>=20000,0.05,IF(G91>=10000,0.1,IF(G91>=5000,0.2,IF(G91>=1000,0.3,IF(G91>=0,0.4,{0}))))))} | P91: =IF(AND(B91="",C91=""),"",ROUND(H91*O91,2)) | Q91: 元件 | T91: 0
A92: =ROW()-ROW(A$83) | B92: 电抗器 | C92: LVR 7% 50Kvar 400V/50Hz | D92: 甲供/施耐德电气 | E92: 只 | F92: 3 | G92: =IF(AND(B92="",C92=""),"",ROUND(M92*L92*N92,2)) | H92: =IF(AND(B92="",C92=""),"",ROUND(F92*G92,2)) | J92: =IF(AND(B92="",C92=""),"",ROUND(M92*N92,2)) | K92: =IF(AND(B92="",C92=""),"",ROUND(J92*F92,2)) | L92: 1 | M92: 1e-07 | N92: 0 | O92: {=IF(AND(B92="",C92=""),"",IF(G92>=20000,0.05,IF(G92>=10000,0.1,IF(G92>=5000,0.2,IF(G92>=1000,0.3,IF(G92>=0,0.4,{0}))))))} | P92: =IF(AND(B92="",C92=""),"",ROUND(H92*O92,2)) | Q92: 元件 | T92: 0
A93: =ROW()-ROW(A$83) | B93: SVG | C93: AccuSine PQU 50kvar 机架式产品组合 | D93: 甲供/施耐德电气 | E93: 只 | F93: =IF(AND(B93="",C93=""),"",1) | G93: =IF(AND(B93="",C93=""),"",ROUND(M93*L93*N93,2)) | H93: =IF(AND(B93="",C93=""),"",ROUND(F93*G93,2)) | J93: =IF(AND(B93="",C93=""),"",ROUND(M93*N93,2)) | K93: =IF(AND(B93="",C93=""),"",ROUND(J93*F93,2)) | L93: 1 | M93: 1e-07 | N93: 0 | O93: {=IF(AND(B93="",C93=""),"",IF(G93>=20000,0.05,IF(G93>=10000,0.1,IF(G93>=5000,0.2,IF(G93>=1000,0.3,IF(G93>=0,0.4,{0}))))))} | P93: =IF(AND(B93="",C93=""),"",ROUND(H93*O93,2)) | Q93: 元件 | T93: 0
A94: =ROW()-ROW(A$83) | B94: 熔断器 | C94: NT00 gG 690V/160A+NT00（新底座） | D94: 铭熔 | E94: 只 | F94: 15 | G94: =IF(AND(B94="",C94=""),"",ROUND(M94*L94*N94,2)) | H94: =IF(AND(B94="",C94=""),"",ROUND(F94*G94,2)) | J94: =IF(AND(B94="",C94=""),"",ROUND(M94*N94,2)) | K94: =IF(AND(B94="",C94=""),"",ROUND(J94*F94,2)) | L94: 1 | M94: 23.8 | N94: 1 | O94: {=IF(AND(B94="",C94=""),"",IF(G94>=20000,0.05,IF(G94>=10000,0.1,IF(G94>=5000,0.2,IF(G94>=1000,0.3,IF(G94>=0,0.4,{0}))))))} | P94: =IF(AND(B94="",C94=""),"",ROUND(H94*O94,2)) | Q94: 元件 | T94: 0
A95: =ROW()-ROW(A$83) | B95: 避雷器 | C95: HY1.5W-0.28/1.3 硅胶 | D95: 苏州中联 | E95: 只 | F95: 3 | G95: =IF(AND(B95="",C95=""),"",ROUND(M95*L95*N95,2)) | H95: =IF(AND(B95="",C95=""),"",ROUND(F95*G95,2)) | J95: =IF(AND(B95="",C95=""),"",ROUND(M95*N95,2)) | K95: =IF(AND(B95="",C95=""),"",ROUND(J95*F95,2)) | L95: 1 | M95: 15 | N95: 1 | O95: {=IF(AND(B95="",C95=""),"",IF(G95>=20000,0.05,IF(G95>=10000,0.1,IF(G95>=5000,0.2,IF(G95>=1000,0.3,IF(G95>=0,0.4,{0}))))))} | P95: =IF(AND(B95="",C95=""),"",ROUND(H95*O95,2)) | Q95: 元件 | T95: 0
A96: =ROW()-ROW(A$83) | B96: 熔断器 | C96: UK5-HESI | D96: 菲尼克斯 | E96: 只 | F96: 4 | G96: =IF(AND(B96="",C96=""),"",ROUND(M96*L96*N96,2)) | H96: =IF(AND(B96="",C96=""),"",ROUND(F96*G96,2)) | J96: =IF(AND(B96="",C96=""),"",ROUND(M96*N96,2)) | K96: =IF(AND(B96="",C96=""),"",ROUND(J96*F96,2)) | L96: 1 | M96: 7 | N96: 1 | O96: {=IF(AND(B96="",C96=""),"",IF(G96>=20000,0.05,IF(G96>=10000,0.1,IF(G96>=5000,0.2,IF(G96>=1000,0.3,IF(G96>=0,0.4,{0}))))))} | P96: =IF(AND(B96="",C96=""),"",ROUND(H96*O96,2)) | Q96: 元件 | T96: 0
A97: =ROW()-ROW(A$83) | B97: 温控器 | C97: JWT6011F | D97: 上海雷普 | E97: 只 | F97: =IF(AND(B97="",C97=""),"",1) | G97: =IF(AND(B97="",C97=""),"",ROUND(M97*L97*N97,2)) | H97: =IF(AND(B97="",C97=""),"",ROUND(F97*G97,2)) | J97: =IF(AND(B97="",C97=""),"",ROUND(M97*N97,2)) | K97: =IF(AND(B97="",C97=""),"",ROUND(J97*F97,2)) | L97: =IF(AND(B97="",C97=""),"",1) | M97: 25 | N97: =IF(AND(B97="",C97=""),"",1) | O97: {=IF(AND(B97="",C97=""),"",IF(G97>=20000,0.05,IF(G97>=10000,0.1,IF(G97>=5000,0.2,IF(G97>=1000,0.3,IF(G97>=0,0.4,{0}))))))} | P97: =IF(AND(B97="",C97=""),"",ROUND(H97*O97,2)) | Q97: =IF(AND(B97="",C97=""),"","元件")
A98: =ROW()-ROW(A$83) | B98: 散热风扇 | D98: KAKU | E98: 只 | F98: 3 | G98: =IF(AND(B98="",C98=""),"",ROUND(M98*L98*N98,2)) | H98: =IF(AND(B98="",C98=""),"",ROUND(F98*G98,2)) | J98: =IF(AND(B98="",C98=""),"",ROUND(M98*N98,2)) | K98: =IF(AND(B98="",C98=""),"",ROUND(J98*F98,2)) | L98: 1 | M98: 175 | N98: 1 | O98: {=IF(AND(B98="",C98=""),"",IF(G98>=20000,0.05,IF(G98>=10000,0.1,IF(G98>=5000,0.2,IF(G98>=1000,0.3,IF(G98>=0,0.4,{0}))))))} | P98: =IF(AND(B98="",C98=""),"",ROUND(H98*O98,2)) | Q98: 元件 | T98: 0
A99: =ROW()-ROW(A$83) | B99: 水平排2500A | C99: TMY 3*(2*125*5)+1*125*5+2*50*5 | D99: 国产优质 | E99: 米 | F99: 1 | G99: =IF(AND(B99="",C99=""),"",ROUND(M99*L99*N99,2)) | H99: =IF(AND(B99="",C99=""),"",ROUND(F99*G99,2)) | J99: =IF(AND(B99="",C99=""),"",ROUND(M99*N99,2)) | K99: =IF(AND(B99="",C99=""),"",ROUND(J99*F99,2)) | L99: 1 | M99: 3633.9201 | N99: 1 | O99: {=IF(AND(B99="",C99=""),"",IF(G99>=20000,0.05,IF(G99>=10000,0.1,IF(G99>=5000,0.2,IF(G99>=1000,0.3,IF(G99>=0,0.4,{0}))))))} | P99: =IF(AND(B99="",C99=""),"",ROUND(H99*O99,2)) | Q99: 母排 | T99: 0
A100: =ROW()-ROW(A$83) | B100: 连接铜排 | C100: TMY 1*60*5 | D100: 国产优质 | E100: 米 | F100: 3 | G100: =IF(AND(B100="",C100=""),"",ROUND(M100*L100*N100,2)) | H100: =IF(AND(B100="",C100=""),"",ROUND(F100*G100,2)) | J100: =IF(AND(B100="",C100=""),"",ROUND(M100*N100,2)) | K100: =IF(AND(B100="",C100=""),"",ROUND(J100*F100,2)) | L100: 1 | M100: 223.62585 | N100: 1 | O100: {=IF(AND(B100="",C100=""),"",IF(G100>=20000,0.05,IF(G100>=10000,0.1,IF(G100>=5000,0.2,IF(G100>=1000,0.3,IF(G100>=0,0.4,{0}))))))} | P100: =IF(AND(B100="",C100=""),"",ROUND(H100*O100,2)) | Q100: 母排 | T100: 0
A101: =ROW()-ROW(A$83) | B101: 导线及辅料 | D101: 国产优质 | E101: 套 | F101: 1 | G101: =IF(AND(B101="",C101=""),"",ROUND(M101*L101*N101,2)) | H101: =IF(AND(B101="",C101=""),"",ROUND(F101*G101,2)) | J101: =IF(AND(B101="",C101=""),"",ROUND(M101*N101,2)) | K101: =IF(AND(B101="",C101=""),"",ROUND(J101*F101,2)) | L101: 1 | M101: 1500 | N101: 1 | O101: {=IF(AND(B101="",C101=""),"",IF(G101>=20000,0.05,IF(G101>=10000,0.1,IF(G101>=5000,0.2,IF(G101>=1000,0.3,IF(G101>=0,0.4,{0}))))))} | P101: =IF(AND(B101="",C101=""),"",ROUND(H101*O101,2)) | Q101: 辅料 | T101: 0
A102: =ROW()-ROW(A$83) | B102: Blokset柜 | C102: 1000W*1000D*2200H | D102: 清科 | E102: 台 | F102: 1 | G102: =IF(AND(B102="",C102=""),"",ROUND(M102*L102*N102,2)) | H102: =IF(AND(B102="",C102=""),"",ROUND(F102*G102,2)) | J102: =IF(AND(B102="",C102=""),"",ROUND(M102*N102,2)) | K102: =IF(AND(B102="",C102=""),"",ROUND(J102*F102,2)) | L102: 1 | M102: 4346 | N102: 1 | O102: {=IF(AND(B102="",C102=""),"",IF(G102>=20000,0.05,IF(G102>=10000,0.1,IF(G102>=5000,0.2,IF(G102>=1000,0.3,IF(G102>=0,0.4,{0}))))))} | P102: =IF(AND(B102="",C102=""),"",ROUND(H102*O102,2)) | Q102: 箱体 | T102: 0
A103: =ROW()-ROW(A$83) | F103: =IF(AND(B103="",C103=""),"",1) | G103: =IF(AND(B103="",C103=""),"",ROUND(M103*L103*N103,2)) | H103: =IF(AND(B103="",C103=""),"",ROUND(F103*G103,2)) | J103: =IF(AND(B103="",C103=""),"",ROUND(M103*N103,2)) | K103: =IF(AND(B103="",C103=""),"",ROUND(J103*F103,2)) | L103: =IF(AND(B103="",C103=""),"",1) | N103: =IF(AND(B103="",C103=""),"",1) | O103: {=IF(AND(B103="",C103=""),"",IF(G103>=20000,0.05,IF(G103>=10000,0.1,IF(G103>=5000,0.2,IF(G103>=1000,0.3,IF(G103>=0,0.4,{0}))))))} | P103: =IF(AND(B103="",C103=""),"",ROUND(H103*O103,2)) | Q103: =IF(AND(B103="",C103=""),"","元件")
A104: =ROW()-ROW(A$83) | F104: =IF(AND(B104="",C104=""),"",1) | G104: =IF(AND(B104="",C104=""),"",ROUND(M104*L104*N104,2)) | H104: =IF(AND(B104="",C104=""),"",ROUND(F104*G104,2)) | J104: =IF(AND(B104="",C104=""),"",ROUND(M104*N104,2)) | K104: =IF(AND(B104="",C104=""),"",ROUND(J104*F104,2)) | L104: =IF(AND(B104="",C104=""),"",1) | N104: =IF(AND(B104="",C104=""),"",1) | O104: {=IF(AND(B104="",C104=""),"",IF(G104>=20000,0.05,IF(G104>=10000,0.1,IF(G104>=5000,0.2,IF(G104>=1000,0.3,IF(G104>=0,0.4,{0}))))))} | P104: =IF(AND(B104="",C104=""),"",ROUND(H104*O104,2)) | Q104: =IF(AND(B104="",C104=""),"","元件")
A105: =ROW()-ROW(A$83) | B105: 小计 | H105: =ROUND(SUM(H83:INDEX(H:H,ROW()-1)),2) | K105: =ROUND(SUM(K83:INDEX(K:K,ROW()-1)),2) | V105: {=ROUND(SUMPRODUCT(F83:INDEX(F:F,ROW()-1),V83:INDEX(V:V,ROW()-1)),2)} | W105: {=ROUND(SUMPRODUCT(F83:INDEX(F:F,ROW()-1),W83:INDEX(W:W,ROW()-1)),2)}
A106: =ROW()-ROW(A$83) | B106: 成套费 | H106: 944.76 | K106: 944.76
...
